Workbook
Name _11__2: #REF!
Name bbss: 0.533

Sheet G.G.Variables
E2: GASTOS GENERALES VARIABLES DEL PAQUETE 08
E4: =+'[1]Res. G.G'!E3 -> “CONSTRUCCIÓN DEL SISTEMA DE DRENAJE URBANO EN EL SECTOR JESÚS MARÍA – CANAL Y OBRAS DE ESTABILIZACIÓN EN LAS LADERAS DEL SECTOR JESÚS MARÍA (PAQUETE 08)” | F4: =+'[1]Res. G.G'!K4 -> 45894
C7: ANÁLISIS DE GASTOS GENERALES VARIABLES
C8: ='[1]Res. G.G'!E8 -> 9.5
C11: ÍTEM | D11: CUENTA COSTOS | E11: DESCRIPCIÓN | F11: P. PARCIAL (S)
C12: 1 | D12: PQ.08.601 | E12: REMUNERACIÓN PERSONAL PROFESIONAL-TECNICO-ADMINISTRATIVO-AUXILIAR, INCLUYE BENEFICIOS SOCIALES | F12: 3384414.4 | M12: EJECUCIÓN | W12: CIERRE COMERCIAL | Z12: TOTAL
C13: 1.01 | E13: REMUNERACIÓN PERSONAL PROFESIONAL | F13: 2863579.3 | M13: MES 1 | N13: MES 2 | O13: MES 3 | P13: MES 4 | Q13: MES 5 | R13: MES 6 | S13: MES 7 | T13: MES 8 | U13: MES 9 | V13: MES 10 | W13: MES 12 | X13: MES 13
C14: 1.01.01 | E14: Ingeniero Residente de Obra (*) | F14: 331733.41 | J14: 19000 | K14: =+IF(#REF!="FORÁNEO",J14+1750,J14) -> #REF! | M14: =+'G.G.Variables'!#REF!*[1]Histograma!I11 -> #REF! | N14: =+'G.G.Variables'!#REF!*[1]Histograma!J11 -> #REF! | O14: =+'G.G.Variables'!#REF!*[1]Histograma!K11 -> #REF! | P14: =+'G.G.Variables'!#REF!*[1]Histograma!L11 -> #REF! | Q14: =+'G.G.Variables'!#REF!*[1]Histograma!M11 -> #REF! | R14: =+'G.G.Variables'!#REF!*[1]Histograma!N11 -> #REF! | S14: =+'G.G.Variables'!#REF!*[1]Histograma!O11 -> #REF! | T14: =+'G.G.Variables'!#REF!*[1]Histograma!P11 -> #REF! | ... X14: =+'G.G.Variables'!#REF!*[1]Histograma!T11 -> #REF! | Z14: =+SUM(M14:X14) -> #REF!
C15: 1.01.02 | E15: Jefe de Producción | F15: 140155.83 | J15: 12000 | K15: =+IF(#REF!="FORÁNEO",J15+1750,J15) -> #REF! | M15: =+'G.G.Variables'!#REF!*[1]Histograma!I12 -> #REF! | N15: =+'G.G.Variables'!#REF!*[1]Histograma!J12 -> #REF! | O15: =+'G.G.Variables'!#REF!*[1]Histograma!K12 -> #REF! | P15: =+'G.G.Variables'!#REF!*[1]Histograma!L12 -> #REF! | Q15: =+'G.G.Variables'!#REF!*[1]Histograma!M12 -> #REF! | R15: =+'G.G.Variables'!#REF!*[1]Histograma!N12 -> #REF! | S15: =+'G.G.Variables'!#REF!*[1]Histograma!O12 -> #REF! | T15: =+'G.G.Variables'!#REF!*[1]Histograma!P12 -> #REF! | ... X15: =+'G.G.Variables'!#REF!*[1]Histograma!T12 -> #REF! | Z15: =+SUM(M15:X15) -> #REF!
C16: 1.01.03 | E16: Ingeniero de Producción 1 | F16: 102758.74 | J16: 10000 | K16: =+IF(#REF!="FORÁNEO",J16+1750,J16) -> #REF! | M16: =+'G.G.Variables'!#REF!*[1]Histograma!I13 -> #REF! | N16: =+'G.G.Variables'!#REF!*[1]Histograma!J13 -> #REF! | O16: =+'G.G.Variables'!#REF!*[1]Histograma!K13 -> #REF! | P16: =+'G.G.Variables'!#REF!*[1]Histograma!L13 -> #REF! | Q16: =+'G.G.Variables'!#REF!*[1]Histograma!M13 -> #REF! | R16: =+'G.G.Variables'!#REF!*[1]Histograma!N13 -> #REF! | S16: =+'G.G.Variables'!#REF!*[1]Histograma!O13 -> #REF! | T16: =+'G.G.Variables'!#REF!*[1]Histograma!P13 -> #REF! | ... X16: =+'G.G.Variables'!#REF!*[1]Histograma!T13 -> #REF! | Z16: =+SUM(M16:X16) -> #REF!
C17: 1.01.04 | E17: Ingeniero de Producción 2 | F17: 102758.74 | M17: =+'G.G.Variables'!#REF!*[1]Histograma!I14 -> #REF! | N17: =+'G.G.Variables'!#REF!*[1]Histograma!J14 -> #REF! | O17: =+'G.G.Variables'!#REF!*[1]Histograma!K14 -> #REF! | P17: =+'G.G.Variables'!#REF!*[1]Histograma!L14 -> #REF! | Q17: =+'G.G.Variables'!#REF!*[1]Histograma!M14 -> #REF! | R17: =+'G.G.Variables'!#REF!*[1]Histograma!N14 -> #REF! | S17: =+'G.G.Variables'!#REF!*[1]Histograma!O14 -> #REF! | T17: =+'G.G.Variables'!#REF!*[1]Histograma!P14 -> #REF! | ... X17: =+'G.G.Variables'!#REF!*[1]Histograma!T14 -> #REF! | Z17: =+SUM(M17:X17) -> #REF!
C18: 1.01.05 | E18: Jefe de Oficina Técnica (*) | F18: 228208.35 | J18: 12000 | K18: =+IF(#REF!="FORÁNEO",J18+1750,J18) -> #REF! | M18: =+'G.G.Variables'!#REF!*[1]Histograma!I15 -> #REF! | N18: =+'G.G.Variables'!#REF!*[1]Histograma!J15 -> #REF! | O18: =+'G.G.Variables'!#REF!*[1]Histograma!K15 -> #REF! | P18: =+'G.G.Variables'!#REF!*[1]Histograma!L15 -> #REF! | Q18: =+'G.G.Variables'!#REF!*[1]Histograma!M15 -> #REF! | R18: =+'G.G.Variables'!#REF!*[1]Histograma!N15 -> #REF! | S18: =+'G.G.Variables'!#REF!*[1]Histograma!O15 -> #REF! | T18: =+'G.G.Variables'!#REF!*[1]Histograma!P15 -> #REF! | ... X18: =+'G.G.Variables'!#REF!*[1]Histograma!T15 -> #REF! | Z18: =+SUM(M18:X18) -> #REF!
C19: 1.01.06 | E19: Ingeniero de Metrados y Valorizaciones (*) | F19: 188391.02 | J19: 10000 | K19: =+IF(#REF!="FORÁNEO",J19+1750,J19) -> #REF! | M19: =+'G.G.Variables'!#REF!*[1]Histograma!I16 -> #REF! | N19: =+'G.G.Variables'!#REF!*[1]Histograma!J16 -> #REF! | O19: =+'G.G.Variables'!#REF!*[1]Histograma!K16 -> #REF! | P19: =+'G.G.Variables'!#REF!*[1]Histograma!L16 -> #REF! | Q19: =+'G.G.Variables'!#REF!*[1]Histograma!M16 -> #REF! | R19: =+'G.G.Variables'!#REF!*[1]Histograma!N16 -> #REF! | S19: =+'G.G.Variables'!#REF!*[1]Histograma!O16 -> #REF! | T19: =+'G.G.Variables'!#REF!*[1]Histograma!P16 -> #REF! | ... X19: =+'G.G.Variables'!#REF!*[1]Histograma!T16 -> #REF! | Z19: =+SUM(M19:X19) -> #REF!
C20: 1.01.07 | E20: Ingeniero de Planemiento y Programación | F20: 154138.1 | J20: 10000 | K20: =+IF(#REF!="FORÁNEO",J20+1750,J20) -> #REF! | M20: =+'G.G.Variables'!#REF!*[1]Histograma!I17 -> #REF! | N20: =+'G.G.Variables'!#REF!*[1]Histograma!J17 -> #REF! | O20: =+'G.G.Variables'!#REF!*[1]Histograma!K17 -> #REF! | P20: =+'G.G.Variables'!#REF!*[1]Histograma!L17 -> #REF! | Q20: =+'G.G.Variables'!#REF!*[1]Histograma!M17 -> #REF! | R20: =+'G.G.Variables'!#REF!*[1]Histograma!N17 -> #REF! | S20: =+'G.G.Variables'!#REF!*[1]Histograma!O17 -> #REF! | T20: =+'G.G.Variables'!#REF!*[1]Histograma!P17 -> #REF! | ... X20: =+'G.G.Variables'!#REF!*[1]Histograma!T17 -> #REF! | Z20: =+SUM(M20:X20) -> #REF!
C21: 1.01.08 | E21: Ingeniero Ambiental | F21: 102758.74 | J21: 10000 | K21: =+IF(#REF!="FORÁNEO",J21+1750,J21) -> #REF! | M21: =+'G.G.Variables'!#REF!*[1]Histograma!I18 -> #REF! | N21: =+'G.G.Variables'!#REF!*[1]Histograma!J18 -> #REF! | O21: =+'G.G.Variables'!#REF!*[1]Histograma!K18 -> #REF! | P21: =+'G.G.Variables'!#REF!*[1]Histograma!L18 -> #REF! | Q21: =+'G.G.Variables'!#REF!*[1]Histograma!M18 -> #REF! | R21: =+'G.G.Variables'!#REF!*[1]Histograma!N18 -> #REF! | S21: =+'G.G.Variables'!#REF!*[1]Histograma!O18 -> #REF! | T21: =+'G.G.Variables'!#REF!*[1]Histograma!P18 -> #REF! | ... X21: =+'G.G.Variables'!#REF!*[1]Histograma!T18 -> #REF! | Z21: =+SUM(M21:X21) -> #REF!
C22: 1.01.09 | E22: Responsable SSOMA 1 | F22: 162701.33 | J22: 10000 | K22: =+IF(#REF!="FORÁNEO",J22+1750,J22) -> #REF! | M22: =+'G.G.Variables'!#REF!*[1]Histograma!I19 -> #REF! | N22: =+'G.G.Variables'!#REF!*[1]Histograma!J19 -> #REF! | O22: =+'G.G.Variables'!#REF!*[1]Histograma!K19 -> #REF! | P22: =+'G.G.Variables'!#REF!*[1]Histograma!L19 -> #REF! | Q22: =+'G.G.Variables'!#REF!*[1]Histograma!M19 -> #REF! | R22: =+'G.G.Variables'!#REF!*[1]Histograma!N19 -> #REF! | S22: =+'G.G.Variables'!#REF!*[1]Histograma!O19 -> #REF! | T22: =+'G.G.Variables'!#REF!*[1]Histograma!P19 -> #REF! | ... X22: =+'G.G.Variables'!#REF!*[1]Histograma!T19 -> #REF! | Z22: =+SUM(M22:X22) -> #REF!
C23: 1.01.10 | E23: Responsable SSOMA 2 | F23: 162701.33 | M23: =+'G.G.Variables'!#REF!*[1]Histograma!I20 -> #REF! | N23: =+'G.G.Variables'!#REF!*[1]Histograma!J20 -> #REF! | O23: =+'G.G.Variables'!#REF!*[1]Histograma!K20 -> #REF! | P23: =+'G.G.Variables'!#REF!*[1]Histograma!L20 -> #REF! | Q23: =+'G.G.Variables'!#REF!*[1]Histograma!M20 -> #REF! | R23: =+'G.G.Variables'!#REF!*[1]Histograma!N20 -> #REF! | S23: =+'G.G.Variables'!#REF!*[1]Histograma!O20 -> #REF! | T23: =+'G.G.Variables'!#REF!*[1]Histograma!P20 -> #REF! | ... X23: =+'G.G.Variables'!#REF!*[1]Histograma!T20 -> #REF! | Z23: =+SUM(M23:X23) -> #REF!
C24: 1.01.11 | E24: Prevencionista de obra 1 | F24: 90678.75 | J24: 7000 | K24: =+IF(#REF!="FORÁNEO",J24+1750,J24) -> #REF! | M24: =+'G.G.Variables'!#REF!*[1]Histograma!I21 -> #REF! | N24: =+'G.G.Variables'!#REF!*[1]Histograma!J21 -> #REF! | O24: =+'G.G.Variables'!#REF!*[1]Histograma!K21 -> #REF! | P24: =+'G.G.Variables'!#REF!*[1]Histograma!L21 -> #REF! | Q24: =+'G.G.Variables'!#REF!*[1]Histograma!M21 -> #REF! | R24: =+'G.G.Variables'!#REF!*[1]Histograma!N21 -> #REF! | S24: =+'G.G.Variables'!#REF!*[1]Histograma!O21 -> #REF! | T24: =+'G.G.Variables'!#REF!*[1]Histograma!P21 -> #REF! | ... X24: =+'G.G.Variables'!#REF!*[1]Histograma!T21 -> #REF! | Z24: =+SUM(M24:X24) -> #REF!
C25: 1.01.12 | E25: Prevencionista de obra 2 | F25: 90678.75 | M25: =+'G.G.Variables'!#REF!*[1]Histograma!I22 -> #REF! | N25: =+'G.G.Variables'!#REF!*[1]Histograma!J22 -> #REF! | O25: =+'G.G.Variables'!#REF!*[1]Histograma!K22 -> #REF! | P25: =+'G.G.Variables'!#REF!*[1]Histograma!L22 -> #REF! | Q25: =+'G.G.Variables'!#REF!*[1]Histograma!M22 -> #REF! | R25: =+'G.G.Variables'!#REF!*[1]Histograma!N22 -> #REF! | S25: =+'G.G.Variables'!#REF!*[1]Histograma!O22 -> #REF! | T25: =+'G.G.Variables'!#REF!*[1]Histograma!P22 -> #REF! | ... X25: =+'G.G.Variables'!#REF!*[1]Histograma!T22 -> #REF! | Z25: =+SUM(M25:X25) -> #REF!
C26: 1.01.13 | E26: Especialista BIM | F26: 220244.88 | J26: 12000 | K26: =+IF(#REF!="FORÁNEO",J26+1750,J26) -> #REF! | M26: =+'G.G.Variables'!#REF!*[1]Histograma!I23 -> #REF! | N26: =+'G.G.Variables'!#REF!*[1]Histograma!J23 -> #REF! | O26: =+'G.G.Variables'!#REF!*[1]Histograma!K23 -> #REF! | P26: =+'G.G.Variables'!#REF!*[1]Histograma!L23 -> #REF! | Q26: =+'G.G.Variables'!#REF!*[1]Histograma!M23 -> #REF! | R26: =+'G.G.Variables'!#REF!*[1]Histograma!N23 -> #REF! | S26: =+'G.G.Variables'!#REF!*[1]Histograma!O23 -> #REF! | T26: =+'G.G.Variables'!#REF!*[1]Histograma!P23 -> #REF! | ... X26: =+'G.G.Variables'!#REF!*[1]Histograma!T23 -> #REF! | Z26: =+SUM(M26:X26) -> #REF!
C27: 1.01.14 | E27: Jefe de Calidad | F27: 171264.56 | J27: 11000 | K27: =+IF(#REF!="FORÁNEO",J27+1750,J27) -> #REF! | M27: =+'G.G.Variables'!#REF!*[1]Histograma!I24 -> #REF! | N27: =+'G.G.Variables'!#REF!*[1]Histograma!J24 -> #REF! | O27: =+'G.G.Variables'!#REF!*[1]Histograma!K24 -> #REF! | P27: =+'G.G.Variables'!#REF!*[1]Histograma!L24 -> #REF! | Q27: =+'G.G.Variables'!#REF!*[1]Histograma!M24 -> #REF! | R27: =+'G.G.Variables'!#REF!*[1]Histograma!N24 -> #REF! | S27: =+'G.G.Variables'!#REF!*[1]Histograma!O24 -> #REF! | T27: =+'G.G.Variables'!#REF!*[1]Histograma!P24 -> #REF! | ... X27: =+'G.G.Variables'!#REF!*[1]Histograma!T24 -> #REF! | Z27: =+SUM(M27:X27) -> #REF!
C28: 1.01.15 | E28: Ingeniero de Aseguramiento y Control de Calidad | F28: 125428.42 | J28: 9200 | K28: =+IF(#REF!="FORÁNEO",J28+1750,J28) -> #REF! | M28: =+'G.G.Variables'!#REF!*[1]Histograma!I25 -> #REF! | N28: =+'G.G.Variables'!#REF!*[1]Histograma!J25 -> #REF! | O28: =+'G.G.Variables'!#REF!*[1]Histograma!K25 -> #REF! | P28: =+'G.G.Variables'!#REF!*[1]Histograma!L25 -> #REF! | Q28: =+'G.G.Variables'!#REF!*[1]Histograma!M25 -> #REF! | R28: =+'G.G.Variables'!#REF!*[1]Histograma!N25 -> #REF! | S28: =+'G.G.Variables'!#REF!*[1]Histograma!O25 -> #REF! | T28: =+'G.G.Variables'!#REF!*[1]Histograma!P25 -> #REF! | ... X28: =+'G.G.Variables'!#REF!*[1]Histograma!T25 -> #REF! | Z28: =+SUM(M28:X28) -> #REF!
C29: 1.01.16 | E29: Asistente de Aseguramiento y Control de Calidad 1 | F29: 93533.36 | J29: 7400 | K29: =+IF(#REF!="FORÁNEO",J29+1750,J29) -> #REF! | M29: =+'G.G.Variables'!#REF!*[1]Histograma!I26 -> #REF! | N29: =+'G.G.Variables'!#REF!*[1]Histograma!J26 -> #REF! | O29: =+'G.G.Variables'!#REF!*[1]Histograma!K26 -> #REF! | P29: =+'G.G.Variables'!#REF!*[1]Histograma!L26 -> #REF! | Q29: =+'G.G.Variables'!#REF!*[1]Histograma!M26 -> #REF! | R29: =+'G.G.Variables'!#REF!*[1]Histograma!N26 -> #REF! | S29: =+'G.G.Variables'!#REF!*[1]Histograma!O26 -> #REF! | T29: =+'G.G.Variables'!#REF!*[1]Histograma!P26 -> #REF! | ... X29: =+'G.G.Variables'!#REF!*[1]Histograma!T26 -> #REF! | Z29: =+SUM(M29:X29) -> #REF!
C30: 1.01.17 | E30: Asistente de Aseguramiento y Control de Calidad 2 | F30: 93533.36 | M30: =+'G.G.Variables'!#REF!*[1]Histograma!I27 -> #REF! | N30: =+'G.G.Variables'!#REF!*[1]Histograma!J27 -> #REF! | O30: =+'G.G.Variables'!#REF!*[1]Histograma!K27 -> #REF! | P30: =+'G.G.Variables'!#REF!*[1]Histograma!L27 -> #REF! | Q30: =+'G.G.Variables'!#REF!*[1]Histograma!M27 -> #REF! | R30: =+'G.G.Variables'!#REF!*[1]Histograma!N27 -> #REF! | S30: =+'G.G.Variables'!#REF!*[1]Histograma!O27 -> #REF! | T30: =+'G.G.Variables'!#REF!*[1]Histograma!P27 -> #REF! | ... X30: =+'G.G.Variables'!#REF!*[1]Histograma!T27 -> #REF! | Z30: =+SUM(M30:X30) -> #REF!
C31: 1.01.18 | E31: Especialista Social | F31: 119885.19 | J31: 11000 | K31: =+IF(#REF!="FORÁNEO",J31+1750,J31) -> #REF! | M31: =+'G.G.Variables'!#REF!*[1]Histograma!I28 -> #REF! | N31: =+'G.G.Variables'!#REF!*[1]Histograma!J28 -> #REF! | O31: =+'G.G.Variables'!#REF!*[1]Histograma!K28 -> #REF! | P31: =+'G.G.Variables'!#REF!*[1]Histograma!L28 -> #REF! | Q31: =+'G.G.Variables'!#REF!*[1]Histograma!M28 -> #REF! | R31: =+'G.G.Variables'!#REF!*[1]Histograma!N28 -> #REF! | S31: =+'G.G.Variables'!#REF!*[1]Histograma!O28 -> #REF! | T31: =+'G.G.Variables'!#REF!*[1]Histograma!P28 -> #REF! | ... X31: =+'G.G.Variables'!#REF!*[1]Histograma!T28 -> #REF! | Z31: =+SUM(M31:X31) -> #REF!
C32: 1.01.19 | E32: Arqueólogo | F32: 113520.62 | J32: 11000 | K32: =+IF(#REF!="FORÁNEO",J32+1750,J32) -> #REF! | M32: =+'G.G.Variables'!#REF!*[1]Histograma!I29 -> #REF! | N32: =+'G.G.Variables'!#REF!*[1]Histograma!J29 -> #REF! | O32: =+'G.G.Variables'!#REF!*[1]Histograma!K29 -> #REF! | P32: =+'G.G.Variables'!#REF!*[1]Histograma!L29 -> #REF! | Q32: =+'G.G.Variables'!#REF!*[1]Histograma!M29 -> #REF! | R32: =+'G.G.Variables'!#REF!*[1]Histograma!N29 -> #REF! | S32: =+'G.G.Variables'!#REF!*[1]Histograma!O29 -> #REF! | T32: =+'G.G.Variables'!#REF!*[1]Histograma!P29 -> #REF! | ... X32: =+'G.G.Variables'!#REF!*[1]Histograma!T29 -> #REF! | Z32: =+SUM(M32:X32) -> #REF!
C33: 1.01.20 | E33: Arquitecto Paisajista | F33: 68505.82 | J33: 12326.08 | K33: =+IF(#REF!="FORÁNEO",J33+1750,J33) -> #REF! | M33: =+'G.G.Variables'!#REF!*[1]Histograma!I30 -> #REF! | N33: =+'G.G.Variables'!#REF!*[1]Histograma!J30 -> #REF! | O33: =+'G.G.Variables'!#REF!*[1]Histograma!K30 -> #REF! | P33: =+'G.G.Variables'!#REF!*[1]Histograma!L30 -> #REF! | Q33: =+'G.G.Variables'!#REF!*[1]Histograma!M30 -> #REF! | R33: =+'G.G.Variables'!#REF!*[1]Histograma!N30 -> #REF! | S33: =+'G.G.Variables'!#REF!*[1]Histograma!O30 -> #REF! | T33: =+'G.G.Variables'!#REF!*[1]Histograma!P30 -> #REF! | ... X33: =+'G.G.Variables'!#REF!*[1]Histograma!T30 -> #REF! | Z33: =+SUM(M33:X33) -> #REF!
C34: 1.02 | E34: REMUNERACIÓN PERSONAL ADMINISTRATIVO | F34: 378032.62 | K34: =+IF(#REF!="FORÁNEO",J34+1750,J34) -> #REF!
C35: 1.02.01 | E35: Administrador | F35: 148573.68 | J35: 6200 | K35: =+IF(#REF!="FORÁNEO",J35+1750,J35) -> #REF! | M35: =+#REF! -> #REF! | N35: =+#REF! -> #REF! | O35: =+#REF! -> #REF! | P35: =+#REF! -> #REF! | Q35: =+#REF! -> #REF! | R35: =+#REF! -> #REF! | S35: =+#REF! -> #REF! | T35: =+#REF! -> #REF! | U35: =+#REF!/2 -> #REF! | V35: =+#REF! -> #REF! | W35: =+#REF! -> #REF! | X35: =+W35/2 -> #REF! | Z35: =SUM(M35:X35) -> #REF!
C36: 1.02.02 | E36: Encargado de Logística | F36: 89219.82 | J36: 5500 | K36: =+IF(#REF!="FORÁNEO",J36+1750,J36) -> #REF! | M36: =+#REF! -> #REF! | N36: =+#REF! -> #REF! | O36: =+#REF! -> #REF! | P36: =+#REF! -> #REF! | Q36: =+#REF! -> #REF! | R36: =+#REF! -> #REF! | S36: =+#REF! -> #REF! | T36: =+#REF! -> #REF! | U36: =+#REF!/2 -> #REF! | V36: =+#REF! -> #REF! | W36: =+#REF! -> #REF! | X36: =+W36/2 -> #REF! | Z36: =SUM(M36:X36) -> #REF!
C37: 1.02.03 | E37: Almacenero | F37: 59084.24 | J37: 4200 | K37: =+IF(#REF!="FORÁNEO",J37+1750,J37) -> #REF! | M37: =+#REF! -> #REF! | N37: =+#REF! -> #REF! | O37: =+#REF! -> #REF! | P37: =+#REF! -> #REF! | Q37: =+#REF! -> #REF! | R37: =+#REF! -> #REF! | S37: =+#REF! -> #REF! | T37: =+#REF! -> #REF! | U37: =+#REF!/2 -> #REF! | V37: =+#REF! -> #REF! | Z37: =SUM(M37:X37) -> #REF!
C38: 1.02.04 | E38: Control Documentario (*) | F38: 81154.88 | J38: 5000 | K38: =+IF(#REF!="FORÁNEO",J38+1750,J38) -> #REF! | M38: =+#REF! -> #REF! | N38: =+#REF! -> #REF! | O38: =+#REF! -> #REF! | P38: =+#REF! -> #REF! | Q38: =+#REF! -> #REF! | R38: =+#REF! -> #REF! | S38: =+#REF! -> #REF! | T38: =+#REF! -> #REF! | U38: =+#REF!/2 -> #REF! | V38: =+#REF! -> #REF! | W38: =+#REF! -> #REF! | X38: =+W38/2 -> #REF! | Z38: =SUM(M38:X38) -> #REF!
C39: 1.03 | E39: REMUNERACIÓN PERSONAL AUXILIAR | F39: 142802.43 | K39: =+IF(#REF!="FORÁNEO",J39+1750,J39) -> #REF!
C40: 1.03.01 | E40: Auxiliar Almacenero | F40: 35700.61 | J40: 2500 | K40: =+IF(#REF!="FORÁNEO",J40+1750,J40) -> #REF! | M40: =+#REF! -> #REF! | N40: =+#REF! -> #REF! | O40: =+#REF! -> #REF! | P40: =+#REF! -> #REF! | Q40: =+#REF! -> #REF! | R40: =+#REF! -> #REF! | S40: =+#REF! -> #REF! | T40: =+#REF! -> #REF! | U40: =+#REF!/2 -> #REF! | V40: =+#REF! -> #REF! | Z40: =SUM(M40:X40) -> #REF!
C41: 1.03.02 | E41: Guardianes en Campamento y componente | F41: 107101.82 | J41: 2500 | K41: =+IF(#REF!="FORÁNEO",J41+1750,J41) -> #REF! | M41: =+#REF!*3 -> #REF! | N41: =+#REF!*3 -> #REF! | O41: =+#REF!*3 -> #REF! | P41: =+#REF!*3 -> #REF! | Q41: =+#REF!*3 -> #REF! | R41: =+#REF!*3 -> #REF! | S41: =+#REF!*3 -> #REF! | T41: =+#REF!*3 -> #REF! | U41: =+#REF!*3/2 -> #REF! | V41: =+#REF!*3 -> #REF! | Z41: =SUM(M41:X41) -> #REF!
C42: 2 | D42: PQ.08.602 | E42: CONSUMIBLES, EQUIPOS Y LICENCIAS NO INCLUIDOS EN LOS COSTOS DIRECTOS | F42: 112160 | K42: =+IF(#REF!="FORÁNEO",J42+1750,J42) -> #REF!
C43: 2.01 | E43: Radios de comunicación | F43: 15400 | J43: 700 | K43: =+IF(#REF!="FORÁNEO",J43+1750,J43) -> #REF! | M43: =+F43 -> 15400 | Z43: =SUM(M43:X43) -> 15400
C44: =+C43+0.01 -> 2.02 | E44: Equipos de Cómputo | F44: 66500 | J44: 350 | K44: =+IF(#REF!="FORÁNEO",J44+1750,J44) -> #REF! | M44: =+#REF!*#REF! -> #REF! | N44: =+#REF!*#REF! -> #REF! | O44: =+#REF!*#REF! -> #REF! | P44: =+#REF!*#REF! -> #REF! | Q44: =+#REF!*#REF! -> #REF! | R44: =+#REF!*#REF! -> #REF! | S44: =+#REF!*#REF! -> #REF! | T44: =+#REF!*#REF! -> #REF! | U44: =+#REF!*#REF! -> #REF! | V44: =+#REF!*#REF!/2 -> #REF! | Z44: =SUM(M44:X44) -> #REF!
E45: =+E44 -> Equipos de Cómputo | F45: 4900 | J45: 350 | K45: =+IF(#REF!="FORÁNEO",J45+1750,J45) -> #REF! | M45: =#REF!*2*[1]Histograma!I29 -> #REF! | N45: =#REF!*2*[1]Histograma!J29 -> #REF! | O45: =#REF!*2*[1]Histograma!K29 -> #REF! | P45: =#REF!*2*[1]Histograma!L29 -> #REF! | Q45: =#REF!*2*[1]Histograma!M29 -> #REF! | R45: =#REF!*2*[1]Histograma!N29 -> #REF! | S45: =#REF!*2*[1]Histograma!O29 -> #REF! | T45: =#REF!*2*[1]Histograma!P29 -> #REF! | ... V45: =#REF!*2*[1]Histograma!R29 -> #REF! | Z45: =SUM(M45:X45) -> #REF!
C46: =+C44+0.01 -> 2.03 | E46: Celulares | F46: 17100 | J46: 90 | K46: =+IF(#REF!="FORÁNEO",J46+1750,J46) -> #REF! | M46: =#REF!*#REF! -> #REF! | N46: =#REF!*#REF! -> #REF! | O46: =#REF!*#REF! -> #REF! | P46: =#REF!*#REF! -> #REF! | Q46: =#REF!*#REF! -> #REF! | R46: =#REF!*#REF! -> #REF! | S46: =#REF!*#REF! -> #REF! | T46: =#REF!*#REF! -> #REF! | U46: =#REF!*#REF! -> #REF! | V46: =#REF!*#REF!/2 -> #REF! | Z46: =SUM(M46:X46) -> #REF!
E47: =+E46 -> Celulares | F47: 1260 | J47: 90 | K47: =+IF(#REF!="FORÁNEO",J47+1750,J47) -> #REF! | M47: =#REF!*2*[1]Histograma!I29 -> #REF! | N47: =#REF!*2*[1]Histograma!J29 -> #REF! | O47: =#REF!*2*[1]Histograma!K29 -> #REF! | P47: =#REF!*2*[1]Histograma!L29 -> #REF! | Q47: =#REF!*2*[1]Histograma!M29 -> #REF! | R47: =#REF!*2*[1]Histograma!N29 -> #REF! | S47: =#REF!*2*[1]Histograma!O29 -> #REF! | T47: =#REF!*2*[1]Histograma!P29 -> #REF! | ... V47: =#REF!*2*[1]Histograma!R29 -> #REF! | Z47: =SUM(M47:X47) -> #REF!
C48: =+C46+0.01 -> 2.04 | E48: Consumibles para Arqueología (señalización preventiva con citas y/o mallas de seguridad, implementación de carteles, paneles, charlas de sensibilización) | F48: 7000 | J48: 1000 | K48: =+IF(#REF!="FORÁNEO",J48+1750,J48) -> #REF! | M48: =#REF!*[1]Histograma!I29 -> #REF! | N48: =#REF!*[1]Histograma!J29 -> #REF! | O48: =#REF!*[1]Histograma!K29 -> #REF! | P48: =#REF!*[1]Histograma!L29 -> #REF! | Q48: =#REF!*[1]Histograma!M29 -> #REF! | R48: =#REF!*[1]Histograma!N29 -> #REF! | S48: =#REF!*[1]Histograma!O29 -> #REF! | T48: =#REF!*[1]Histograma!P29 -> #REF! | ... V48: =#REF!*[1]Histograma!R29 -> #REF! | Z48: =SUM(M48:X48) -> #REF!
C49: 3 | D49: PQ.08.603 | E49: VEHÍCULOS (INCLUYE CONDUCTOR, COMBUSTIBLE, MANTENIMIENTO) | F49: 553072.06 | K49: =+IF(#REF!="FORÁNEO",J49+1750,J49) -> #REF!
C50: =+C49+0.01 -> 3.01 | E50: Camioneta Pick Up Cabina Doble 4x4 (Ejec. Obra) | F50: 339322.06 | J50: 12600 | K50: =+IF(#REF!="FORÁNEO",J50+1750,J50) -> #REF! | M50: =#REF!*#REF! -> #REF! | N50: =#REF!*#REF! -> #REF! | O50: =#REF!*#REF! -> #REF! | P50: =#REF!*#REF! -> #REF! | Q50: =#REF!*#REF! -> #REF! | R50: =#REF!*#REF! -> #REF! | S50: =#REF!*#REF! -> #REF! | T50: =#REF!*#REF! -> #REF! | U50: =#REF!*#REF! -> #REF! | V50: =#REF!*#REF!/2 -> #REF! | W50: =#REF!*#REF! -> #REF! | X50: =+W50/2 -> #REF! | Z50: =SUM(M50:X50) -> #REF!
C51: =+C50+0.01 -> 3.02 | E51: Camión Abastecedor de combustible | F51: 71250 | J51: 2000 | K51: =+IF(#REF!="FORÁNEO",J51+1750,J51) -> #REF! | M51: =#REF!*#REF! -> #REF! | N51: =#REF!*#REF! -> #REF! | O51: =#REF!*#REF! -> #REF! | P51: =#REF!*#REF! -> #REF! | Q51: =#REF!*#REF! -> #REF! | R51: =#REF!*#REF! -> #REF! | S51: =#REF!*#REF! -> #REF! | T51: =#REF!*#REF! -> #REF! | U51: =#REF!*#REF! -> #REF! | V51: =#REF!*#REF!/2 -> #REF! | Z51: =SUM(M51:X51) -> #REF!
C52: =+C51+0.01 -> 3.03 | E52: Camión Baranda 5 tn | F52: 142500 | J52: 1440 | K52: =+IF(#REF!="FORÁNEO",J52+1750,J52) -> #REF! | M52: =#REF!*#REF! -> #REF! | N52: =#REF!*#REF! -> #REF! | O52: =#REF!*#REF! -> #REF! | P52: =#REF!*#REF! -> #REF! | Q52: =#REF!*#REF! -> #REF! | R52: =#REF!*#REF! -> #REF! | S52: =#REF!*#REF! -> #REF! | T52: =#REF!*#REF! -> #REF! | U52: =#REF!*#REF! -> #REF! | V52: =#REF!*#REF!/2 -> #REF! | Z52: =SUM(M52:X52) -> #REF!
C53: 4 | D53: PQ.08.604 | E53: PLAN DE SEGURIDAD Y SALUD EN EL TRABAJO | F53: 51503.84 | K53: =+IF(#REF!="FORÁNEO",J53+1750,J53) -> #REF!
C54: =+C53+0.01 -> 4.01 | E54: Implementos de Seguridad Profesionales | F54: 9145.6 | J54: 228.64 | K54: =+IF(#REF!="FORÁNEO",J54+1750,J54) -> #REF! | M54: 1371.84 | N54: 1371.84 | O54: 685.92 | P54: 228.64 | Q54: 0 | R54: =3658.24+1829.12 -> 5487.36 | Z54: =SUM(M54:X54) -> 9145.6
C55: =+C54+0.01 -> 4.02 | E55: Implementos de Seguridad Téc., Adm. y Auxiliares | F55: 3658.24 | J55: 228.64 | K55: =+IF(#REF!="FORÁNEO",J55+1750,J55) -> #REF! | M55: =#REF!*8 -> #REF! | R55: =#REF!*8 -> #REF! | Z55: =SUM(M55:X55) -> #REF!
C56: =+C55+0.01 -> 4.03 | E56: Examenes medicos - Profesionales (**) | F56: 6000 | J56: 150 | K56: =+IF(#REF!="FORÁNEO",J56+1750,J56) -> #REF! | M56: 900 | N56: 900 | O56: 450 | P56: 1500 | Q56: 0 | R56: 0 | S56: 150 | T56: 450 | U56: 750 | V56: 150 | W56: 0 | X56: 750 | Z56: =SUM(M56:X56) -> 6000
C57: =C56+0.01 -> 4.04 | E57: Examenes medicos - Administrativo (**) | F57: 1200 | J57: 150 | K57: =+IF(#REF!="FORÁNEO",J57+1750,J57) -> #REF! | M57: 750 | X57: 450 | Z57: =SUM(M57:X57) -> 1200
C58: =+C57+0.01 -> 4.05 | E58: Examenes medicos - Auxiliares (**) | F58: 1200 | J58: 150 | K58: =+IF(#REF!="FORÁNEO",J58+1750,J58) -> #REF! | M58: 1200 | Z58: =SUM(M58:X58) -> 1200
C59: =+C58+0.01 -> 4.06 | E59: Examenes médicos - Obreros (**) | F59: 30300 | J59: 150 | K59: =+IF(#REF!="FORÁNEO",J59+1750,J59) -> #REF! | M59: 30300 | Z59: =SUM(M59:X59) -> 30300
C60: 5 | D60: PQ.08.605 | E60: GASTOS DE OFICINA EN CAMPAMENTO | F60: 56460.4 | K60: =+IF(#REF!="FORÁNEO",J60+1750,J60) -> #REF!
C61: =+C60+0.01 -> 5.01 | E61: Fotocopias y escaneo | F61: 13442.5 | J61: 1500 | K61: =+IF(#REF!="FORÁNEO",J61+1750,J61) -> #REF! | M61: =#REF! -> #REF! | N61: =M61 -> #REF! | O61: =N61 -> #REF! | P61: =O61 -> #REF! | Q61: =P61 -> #REF! | R61: =Q61 -> #REF! | S61: =R61 -> #REF! | T61: =S61 -> #REF! | U61: =T61 -> #REF! | V61: =U61/2 -> #REF! | Z61: =SUM(M61:V61) -> #REF!
C62: =+C61+0.01 -> 5.02 | E62: Ploteos | F62: 11400 | J62: 1250 | K62: =+IF(#REF!="FORÁNEO",J62+1750,J62) -> #REF! | M62: =#REF! -> #REF! | N62: =M62 -> #REF! | O62: =N62 -> #REF! | P62: =O62 -> #REF! | Q62: =P62 -> #REF! | R62: =Q62 -> #REF! | S62: =R62 -> #REF! | T62: =S62 -> #REF! | U62: =T62 -> #REF! | V62: =U62/2 -> #REF! | Z62: =SUM(M62:V62) -> #REF!
C63: =+C62+0.01 -> 5.03 | E63: Útiles de oficina | F63: 26867.9 | J63: 1000 | K63: =+IF(#REF!="FORÁNEO",J63+1750,J63) -> #REF! | M63: =#REF! -> #REF! | N63: =M63 -> #REF! | O63: =N63 -> #REF! | P63: =O63 -> #REF! | Q63: =P63 -> #REF! | R63: =Q63 -> #REF! | S63: =R63 -> #REF! | T63: =S63 -> #REF! | U63: =T63 -> #REF! | V63: =U63/2 -> #REF! | Z63: =SUM(M63:V63) -> #REF!
C64: =+C63+0.01 -> 5.04 | E64: Varios | F64: 4750 | J64: 500 | K64: =+IF(#REF!="FORÁNEO",J64+1750,J64) -> #REF! | M64: =#REF! -> #REF! | N64: =M64 -> #REF! | O64: =N64 -> #REF! | P64: =O64 -> #REF! | Q64: =P64 -> #REF! | R64: =Q64 -> #REF! | S64: =R64 -> #REF! | T64: =S64 -> #REF! | U64: =T64 -> #REF! | V64: =U64/2 -> #REF! | Z64: =SUM(M64:V64) -> #REF!
C65: 6 | D65: PQ.08.606 | E65: GASTOS FINANCIEROS | F65: 0
C66: =+C65+0.01 -> 6.01 | E66: Garantia de Fiel Cumplimiento del Contrato | F66: 0 | M66: =F66/11 -> 0 | N66: =M66 -> 0 | O66: =N66 -> 0 | P66: =O66 -> 0 | Q66: =P66 -> 0 | R66: =Q66 -> 0 | S66: =R66 -> 0 | T66: =S66 -> 0 | U66: =T66 -> 0 | V66: =U66 -> 0 | Z66: =SUM(M66:V66) -> 0
C67: =+C66+0.01 -> 6.02 | E67: Garantia del Adelanto Directo | F67: 0 | M67: =F67/11 -> 0 | N67: =M67 -> 0 | O67: =N67 -> 0 | P67: =O67 -> 0 | Q67: =P67 -> 0 | R67: =Q67 -> 0 | S67: =R67 -> 0 | T67: =S67 -> 0 | U67: =T67 -> 0 | V67: =U67 -> 0 | Z67: =SUM(M67:V67) -> 0
C68: =+C67+0.01 -> 6.03 | E68: Gastos Bancarios (ITF) | F68: 0 | Z68: =SUM(M68:V68) -> 0
C69: 7 | D69: PQ.08.607 | E69: SEGUROS | F69: 340366.24
C70: =+C69+0.01 -> 7.01 | E70: Seguro de Responsabilidad Civil | F70: 330452.66 | M70: =F70/9.5 -> 34784.491 | N70: =M70 -> 34784.491 | O70: =N70 -> 34784.491 | P70: =O70 -> 34784.491 | Q70: =P70 -> 34784.491 | R70: =Q70 -> 34784.491 | S70: =R70 -> 34784.491 | T70: =S70 -> 34784.491 | U70: =T70 -> 34784.491 | V70: =U70/2 -> 17392.245 | Z70: =SUM(M70:V70) -> 330452.66
C71: =+C70+0.01 -> 7.02 | E71: Costo Por Emisión de Poliza | F71: 9913.58 | M71: =+F71/3 -> 3304.5267 | Q71: =+M71 -> 3304.5267 | U71: =+Q71 -> 3304.5267 | Z71: =SUM(M71:X71) -> 9913.58
C73: TOTAL GASTOS GENERALES VARIABLES | F73: 4497976.9
C75: Consideraciones:
C76: (*) Incluye 2 meses adicionales para Cierre Comercial
C77: (**) Tanto examen médico de ingreso como de salida
C78: Las tarifas de sueldos brutos del personal se actualizarán de acuerdo a lo que nos otorgue una empresa especializada. Este servicio será a Costo Determinado
C79: La cantidad y permanencia de los profesionales para cada puesto estará definida de acuerdo a la necesidad de la ejecución
C82: Nota de Aclaración – Presupuesto para Cierre Comercial
C83: En atención a la observación formulada respecto a la no presentación del “Presupuesto detallado para el Cierre Comercial”, se deja constancia que los costos asociados a esta etapa han sido contemplados dentro del análisis de los Gastos Generales Variables del proyecto.
C84: En el mencionado análisis se incluyen:
C85: - Remuneraciones del personal clave durante la etapa de cierre comercial (Ingeniero Residente, Oficina Técnica, Calidad, SSOMA, entre otros), como se muestra en la columna “Meses (Cierre Comercial)”.
C86: - Medios logísticos requeridos para el cierre, tales como la Camioneta Pick-Up Cabina Doble 4x4, considerada durante 1.5 meses adicionales con todos los gastos operativos incluidos (conductor, combustible y mantenimiento).
C87: Este enfoque integral garantiza la operatividad administrativa, técnica y logística necesaria hasta la liquidación total de obra, de acuerdo con lo establecido en los Términos de Referencia.
C88: De ser requerido, se puede ampliar esta información en un anexo complementario desagregado

Sheet G.G.Fijos
E2: GASTOS GENERALES FIJOS DEL PAQUETE 08
E3: =+'[1]Res. G.G'!E3 -> “CONSTRUCCIÓN DEL SISTEMA DE DRENAJE URBANO EN EL SECTOR JESÚS MARÍA – CANAL Y OBRAS DE ESTABILIZACIÓN EN LAS LADERAS DEL SECTOR JESÚS MARÍA (PAQUETE 08)”
F4: =+'[1]Res. G.G'!K4 -> 45894
C6: ANÁLISIS DE GASTOS GENERALES FIJOS
C7: ='[1]Res. G.G'!E8 -> 9.5
C9: ITEM | D9: CUENTA COSTOS | E9: DESCRIPCION | F9: P. PARCIAL (S)
C10: 1 | D10: PQ.08.701 | E10: CONTRIBUCIÓN A SENCICO | F10: 71122.44
C11: =+C10+0.01 -> 1.01 | E11: SENCICO (0.2% del presupuesto sin IGV)
C14: TOTAL GASTOS GENERALES FIJOS | F14: =+#REF!+F10 -> #REF!
C17: Consideraciones:
C18: No se consideran costos corporativos, dado que estan cubiertos por la Utilidad.
C19: Los costos indicados son estimados, corresponden a los recursos mínimos en que incurre toda empresa en sus oficinas corporativas.

Sheet PPTO
A1: ÍTEM | B1: CUENTA COSTOS | C1: DESCRIPCIÓN | D1: UND. | E1: METRADO | F1: P.U (S/) | G1: P. PARCIAL (S)
A3: 01 | C3: OBRAS PROVISIONALES | G3: =SUM(G4:G10) -> 1938678.5
A4: 01.01 | B4: PQ.08.101 | C4: MOVILIZACION Y DESMOVILIZACION DE EQUIPOS Y/O MAQUINARIAS PAQ-8 | D4: glb | E4: 1 | F4: 520830 | G4: =ROUND(E4*F4,2) -> 520830
A5: 01.02 | B5: PQ.08.105 | C5: CARTEL DE IDENTIFICACION DE LA OBRA DE 3.60 X 2.40 M | D5: und | E5: 2 | F5: 3446.8 | G5: =ROUND(E5*F5,2) -> 6893.6
A6: 01.03 | B6: PQ.08.102 | C6: IMPLEMENTACIÓN DEL PLAN DE GESTION DE TRÁFICO VEHICULAR (PAQ-8) | D6: mes | E6: 11 | F6: 70700.15 | G6: =ROUND(E6*F6,2) -> 777701.65
A7: 01.04 | B7: PQ.08.103 | C7: PLAN DE SALUD, SEGURIDAD Y MEDIO AMBIENTE PAQ-8 | D7: glb | E7: 1 | F7: 326560.17 | G7: =ROUND(E7*F7,2) -> 326560.17
A8: 01.05 | B8: PQ.08.104 | C8: PLAN DE MANEJO AMBIENTAL PAQ-8 | D8: glb | E8: 1 | F8: 122241.55 | G8: =ROUND(E8*F8,2) -> 122241.55
A9: 01.06 | B9: PQ.08.105 | C9: PLAN DE CONTROL CONTRA EL COVID-19 PAQ-8 | D9: glb | E9: 1 | F9: 73343.62 | G9: =ROUND(E9*F9,2) -> 73343.62
A10: 01.07 | B10: PQ.08.105 | C10: PLAN DE MANEJO DE AGUAS PLUVIALES Y SUPERFICIALES (PAQ-08) | D10: glb | E10: 1 | F10: 111107.92 | G10: =ROUND(E10*F10,2) -> 111107.92
A11: 02 | C11: CAMPAMENTO DE OBRA - YALE 3 | G11: =SUM(G12:G35) -> 1250944.1
A12: 02.01 | B12: PQ.08.106 | C12: TRAZO Y REPLANTEO | D12: m2 | E12: 9490 | F12: 3.21 | G12: =ROUND(E12*F12,2) -> 30462.9
A13: 02.02 | B13: PQ.08.106 | C13: PERFILADO Y COMPACTADO PARA CAMPAMENTO | D13: m2 | E13: 9490 | F13: 6.45 | G13: =ROUND(E13*F13,2) -> 61210.5
A14: 02.03 | B14: PQ.08.106 | C14: TRANSPORTE DE MATERIAL GRANULAR, D<=1 KM | D14: m3-km | E14: 1898 | F14: 8.06 | G14: =ROUND(E14*F14,2) -> 15297.88
A15: 02.04 | B15: PQ.08.106 | C15: SUMINISTRO EN PUNTO DE ACOPIO DE MATERIAL DE PRÉSTAMO (AFIRMADO) | D15: m3 | E15: 1898 | F15: 78.24 | G15: =ROUND(E15*F15,2) -> 148499.52
A16: 02.05 | B16: PQ.08.106 | C16: CONFORMACIÓN DE TERRENO CON MATERIAL DE AFIRMADO | D16: m3 | E16: 1898 | F16: 16.49 | G16: =ROUND(E16*F16,2) -> 31298.02
A17: 02.06 | B17: PQ.08.106 | C17: CONFORMACION Y COMPACTACION CON MATERIAL PROPIO | D17: m3 | E17: 2035.2 | F17: 16.49 | G17: =ROUND(E17*F17,2) -> 33560.45
A18: 02.07 | B18: PQ.08.106 | C18: CERCO DE CAMPAMENTO | D18: m | E18: 396 | F18: 191.5 | G18: =ROUND(E18*F18,2) -> 75834
A19: 02.08 | B19: PQ.08.106 | C19: PORTON CAMPAMENTO | D19: und | E19: 1 | F19: 4250 | G19: =ROUND(E19*F19,2) -> 4250
A20: 02.09 | B20: PQ.08.106 | C20: GRUPO ELECTROGENO | D20: mes | E20: 11 | F20: 17879.42 | G20: =ROUND(E20*F20,2) -> 196673.62
A21: 02.10 | B21: PQ.08.106 | C21: SERVICIO DE INTERNET | D21: mes | E21: 11 | F21: 819.18 | G21: =ROUND(E21*F21,2) -> 9010.98
A22: 02.11 | B22: PQ.08.106 | C22: SERVICIO DE LIMPIEZA DE OFICINA | D22: mes | E22: 11 | F22: 3591.94 | G22: =ROUND(E22*F22,2) -> 39511.34
A23: 02.12 | B23: PQ.08.106 | C23: SERVICIO DE SEGURIDAD DE OFICINA | D23: mes | E23: 11 | F23: 12771.34 | G23: =ROUND(E23*F23,2) -> 140484.74
... A35: 02.24 | B35: PQ.08.106 | C35: AREA DE LABORATORIO DE SUELOS, PAVIMENTOS Y CONCRETO | D35: m2 | E35: 35 | F35: 556.31 | G35: =ROUND(E35*F35,2) -> 19470.85
A36: 03 | C36: HABILITACION DE PUNTO DE ACOPIO - YALE 3 | G36: =SUM(G37:G43) -> 525541.31
A37: 03.01 | B37: PQ.08.107 | C37: TRAZO Y REPLANTEO | D37: m2 | E37: 17160 | F37: 3.21 | G37: =ROUND(E37*F37,2) -> 55083.6
A38: 03.02 | B38: PQ.08.107 | C38: PERFILADO Y COMPACTADO PARA PUNTO DE ACOPIO | D38: m2 | E38: 17160 | F38: 3.65 | G38: =ROUND(E38*F38,2) -> 62634
A39: 03.03 | B39: PQ.08.107 | C39: SUMINISTRO EN PUNTO DE ACOPIO DE MATERIAL DE PRÉSTAMO (AFIRMADO) | D39: m3 | E39: 3432 | F39: 78.24 | G39: =ROUND(E39*F39,2) -> 268519.68
A40: 03.04 | B40: PQ.08.107 | C40: CONFORMACIÓN DE TERRENO CON MATERIAL DE AFIRMADO | D40: m3 | E40: 3432 | F40: 16.49 | G40: =ROUND(E40*F40,2) -> 56593.68
A41: 03.05 | B41: PQ.08.107 | C41: CERCO PARA PUNTO DE ACOPIO | D41: m | E41: 384 | F41: 191.5 | G41: =ROUND(E41*F41,2) -> 73536
A42: 03.06 | B42: PQ.08.107 | C42: PORTON PUNTO DE ACOPIO | D42: und | E42: 1 | F42: 4250 | G42: =ROUND(E42*F42,2) -> 4250
A43: 03.07 | B43: PQ.08.107 | C43: CASETA DE GUARDIANÍA | D43: mes | E43: 9 | F43: 547.15 | G43: =ROUND(E43*F43,2) -> 4924.35
A44: 04 | C44: ACCESO A COMPONENTE 4 - CANAL JESUS MARIA | G44: =G45+G57+G69 -> 1633038.2
A45: 04.01 | C45: ACCESO 01 | G45: =SUM(G46:G56) -> 1409109.5
A46: 04.01.01 | B46: PQ.08.108 | C46: TRAZO Y REPLANTEO PARA OBRAS VIALES | D46: km | E46: 1.31 | F46: 1893.96 | G46: =ROUND(E46*F46,2) -> 2481.09
A47: 04.01.02 | B47: PQ.08.108 | C47: EXCAVACION C/MAQ. EN TERRENO NORMAL H<=2M | D47: m3 | E47: 13890.8 | F47: 49.92 | G47: =ROUND(E47*F47,2) -> 693428.74
A48: 04.01.03 | B48: PQ.08.108 | C48: ACARREO DE MATERIAL PROVENIENTE DE EXCAVACIONES, D<= 1KM | D48: m3-km | E48: 13890.8 | F48: 8.06 | G48: =ROUND(E48*F48,2) -> 111959.85
A49: 04.01.04 | B49: PQ.08.108 | C49: RELLENO COMPACTADO CON MATERIAL PROPIO | D49: m3 | E49: 4794.07 | F49: 26.25 | G49: =ROUND(E49*F49,2) -> 125844.34
A50: 04.01.05 | B50: PQ.08.108 | C50: PERFILADO Y COMPACTADO EN ZONAS DE CORTE | D50: m2 | E50: 7680 | F50: 1.95 | G50: =ROUND(E50*F50,2) -> 14976
A51: 04.01.06 | B51: PQ.08.108 | C51: CONFORMACION DE TERRENO CON MATERIAL DE AFIRMADO (E=0.20M) | D51: m3 | E51: 1803.84 | F51: 25.82 | G51: =ROUND(E51*F51,2) -> 46575.15
A52: 04.01.07 | B52: PQ.08.108 | C52: SUMINISTRO EN PUNTO DE ACOPIO DE MATERIAL DE PRESTAMO (AFIRMADO) | D52: m3 | E52: 1803.84 | F52: 78.24 | G52: =ROUND(E52*F52,2) -> 141132.44
A53: 04.01.08 | B53: PQ.08.108 | C53: TRANSPORTE DE MATERIAL GRANULAR, D<=1KM | D53: m3-km | E53: 5806.16 | F53: 8.06 | G53: =ROUND(E53*F53,2) -> 46797.65
A54: 04.01.09 | B54: PQ.08.108 | C54: TRANSPORTE DE MATERIAL GRANULAR, D>1KM | D54: m3-km | E54: 4586.36 | F54: 1.68 | G54: =ROUND(E54*F54,2) -> 7705.08
A55: 04.01.10 | B55: PQ.08.108 | C55: TRANSPORTE DE MATERIAL DE ELIMINACION D<=1KM | D55: m3-km | E55: 12223.9 | F55: 8.82 | G55: =ROUND(E55*F55,2) -> 107814.8
A56: 04.01.11 | B56: PQ.08.108 | C56: TRANSPORTE DE MATERIAL DE ELIMINACION D>1KM | D56: m3-km | E56: 56323.67 | F56: 1.96 | G56: =ROUND(E56*F56,2) -> 110394.39
A57: 04.02 | C57: ACCESO 02 | G57: =SUM(G58:G68) -> 73255.76
A58: 04.02.01 | B58: PQ.08.108 | C58: TRAZO Y REPLANTEO PARA OBRAS VIALES | D58: km | E58: 0.09 | F58: 1893.96 | G58: =ROUND(E58*F58,2) -> 170.46
A59: 04.02.02 | B59: PQ.08.108 | C59: EXCAVACION C/MAQ. EN TERRENO NORMAL H<=2M | D59: m3 | E59: 705.38 | F59: 49.92 | G59: =ROUND(E59*F59,2) -> 35212.57
A60: 04.02.03 | B60: PQ.08.108 | C60: ACARREO DE MATERIAL PROVENIENTE DE EXCAVACIONES, D<= 1KM | D60: m3-km | E60: 705.38 | F60: 8.06 | G60: =ROUND(E60*F60,2) -> 5685.36
A61: 04.02.04 | B61: PQ.08.108 | C61: RELLENO COMPACTADO CON MATERIAL PROPIO | D61: m3 | E61: 166.69 | F61: 26.25 | G61: =ROUND(E61*F61,2) -> 4375.61
A62: 04.02.05 | B62: PQ.08.108 | C62: PERFILADO Y COMPACTADO EN ZONAS DE CORTE | D62: m2 | E62: 566.46 | F62: 1.95 | G62: =ROUND(E62*F62,2) -> 1104.6
A63: 04.02.06 | B63: PQ.08.108 | C63: CONFORMACION DE TERRENO CON MATERIAL DE AFIRMADO (E=0.20M) | D63: m3 | E63: 151.66 | F63: 25.82 | G63: =ROUND(E63*F63,2) -> 3915.86
A64: 04.02.07 | B64: PQ.08.108 | C64: SUMINISTRO EN PUNTO DE ACOPIO DE MATERIAL DE PRESTAMO (AFIRMADO) | D64: m3 | E64: 151.66 | F64: 78.24 | G64: =ROUND(E64*F64,2) -> 11865.88
A65: 04.02.08 | B65: PQ.08.108 | C65: TRANSPORTE DE MATERIAL GRANULAR, D<=1KM | D65: m3-km | E65: 280.14 | F65: 8.06 | G65: =ROUND(E65*F65,2) -> 2257.93
A66: 04.02.09 | B66: PQ.08.108 | C66: TRANSPORTE DE MATERIAL GRANULAR, D>1KM | D66: m3-km | E66: 1342.55 | F66: 1.68 | G66: =ROUND(E66*F66,2) -> 2255.48
A67: 04.02.10 | B67: PQ.08.108 | C67: TRANSPORTE DE MATERIAL DE ELIMINACION D<=1KM | D67: m3-km | E67: 620.73 | F67: 8.82 | G67: =ROUND(E67*F67,2) -> 5474.84
A68: 04.02.11 | B68: PQ.08.108 | C68: TRANSPORTE DE MATERIAL DE ELIMINACION D>1KM | D68: m3-km | E68: 478.15 | F68: 1.96 | G68: =ROUND(E68*F68,2) -> 937.17
A69: 04.03 | C69: ACCESOS 3 Y 4 | G69: =SUM(G70:G80) -> 150672.94
A70: 04.03.01 | B70: PQ.08.108 | C70: TRAZO Y REPLANTEO PARA OBRAS VIALES | D70: km | E70: 0.27 | F70: 1893.96 | G70: =ROUND(E70*F70,2) -> 511.37
A71: 04.03.02 | B71: PQ.08.108 | C71: EXCAVACION C/MAQ. EN TERRENO NORMAL H<=2M | D71: m3 | E71: 543.05 | F71: 49.92 | G71: =ROUND(E71*F71,2) -> 27109.06
A72: 04.03.03 | B72: PQ.08.108 | C72: ACARREO DE MATERIAL PROVENIENTE DE EXCAVACIONES, D<= 1KM | D72: m3-km | E72: 543.05 | F72: 8.06 | G72: =ROUND(E72*F72,2) -> 4376.98
A73: 04.03.04 | B73: PQ.08.108 | C73: RELLENO COMPACTADO CON MATERIAL PROPIO | D73: m3 | E73: 1630.5 | F73: 26.25 | G73: =ROUND(E73*F73,2) -> 42800.63
A74: 04.03.05 | B74: PQ.08.108 | C74: PERFILADO Y COMPACTADO EN ZONAS DE CORTE | D74: m2 | E74: 1620 | F74: 1.95 | G74: =ROUND(E74*F74,2) -> 3159
A75: 04.03.06 | B75: PQ.08.108 | C75: CONFORMACION DE TERRENO CON MATERIAL DE AFIRMADO (E=0.20M) | D75: m3 | E75: 403.08 | F75: 25.82 | G75: =ROUND(E75*F75,2) -> 10407.53
A76: 04.03.07 | B76: PQ.08.108 | C76: SUMINISTRO EN PUNTO DE ACOPIO DE MATERIAL DE PRESTAMO (AFIRMADO) | D76: m3 | E76: 403.08 | F76: 78.24 | G76: =ROUND(E76*F76,2) -> 31536.98
A77: 04.03.08 | B77: PQ.08.108 | C77: TRANSPORTE DE MATERIAL GRANULAR, D<=1KM | D77: m3-km | E77: 1789.54 | F77: 8.06 | G77: =ROUND(E77*F77,2) -> 14423.69
A78: 04.03.09 | B78: PQ.08.108 | C78: TRANSPORTE DE MATERIAL GRANULAR, D>1KM | D78: m3-km | E78: 6792.44 | F78: 1.68 | G78: =ROUND(E78*F78,2) -> 11411.3
A79: 04.03.10 | B79: PQ.08.108 | C79: TRANSPORTE DE MATERIAL DE ELIMINACION D<=1KM | D79: m3-km | E79: 477.88 | F79: 8.82 | G79: =ROUND(E79*F79,2) -> 4214.9
A80: 04.03.11 | B80: PQ.08.108 | C80: TRANSPORTE DE MATERIAL DE ELIMINACION D>1KM | D80: m3-km | E80: 368.11 | F80: 1.96 | G80: =ROUND(E80*F80,2) -> 721.5
A81: 05 | C81: COMPONENTE 04 - CANAL Y ESTABILIZACION DE TALUD - JESUS MARIA | G81: =G82+G90+G139+G170+G198+G224+G250+G276+G302+G324+G346+G368+G390+G414+G442+G489+G519+G552+G579 -> 13212460
A82: 05.01 | C82: CANAL EXISTENTE | G82: =SUM(G83:G89) -> 245749.07
A83: 05.01.01 | B83: PQ.08.201 | C83: CINTA PLASTICA SENALIZADORA PARA LIMITE DE SEGURIDAD DE OBRA | D83: m | E83: 1013.06 | F83: 1.35 | G83: =ROUND(E83*F83,2) -> 1367.63
A84: 05.01.02 | B84: PQ.08.201 | C84: CERCO DE MALLA HDPE DE 1M DE ALTURA PARA LIMITE DE SEGURIDAD DE OBRA | D84: m | E84: 1013.06 | F84: 7.7 | G84: =ROUND(E84*F84,2) -> 7800.56
A85: 05.01.03 | B85: PQ.08.201 | C85: EXCAVACION C/MAQ. EN TERRENO NORMAL H<=2M | D85: m3 | E85: 652.29 | F85: 49.92 | G85: =ROUND(E85*F85,2) -> 32562.32
A86: 05.01.04 | B86: PQ.08.201 | C86: DEMOLICIÓN DE ESTRUCTURAS DE CONCRETO | D86: m3 | E86: 1019.98 | F86: 52.56 | G86: =ROUND(E86*F86,2) -> 53610.15
A87: 05.01.05 | B87: PQ.08.201 | C87: ELIMINACIÓN DE MATERIAL PROVENIENTE DE DEMOLICIONES | D87: m3 | E87: 1019.98 | F87: 138.84 | G87: =ROUND(E87*F87,2) -> 141614.02
A88: 05.01.06 | B88: PQ.08.201 | C88: TRANSPORTE DE MATERIAL DE ELIMINACION D<=1KM | D88: m3-km | E88: 574.09 | F88: 8.82 | G88: =ROUND(E88*F88,2) -> 5063.47
A89: 05.01.07 | B89: PQ.08.201 | C89: TRANSPORTE DE MATERIAL DE ELIMINACION D>1KM | D89: m3-km | E89: 1903.53 | F89: 1.96 | G89: =ROUND(E89*F89,2) -> 3730.92
A90: 05.02 | C90: ESTRUCTURA DE DESCARGA Y DISIPADOR DE ENERGIA (QUEBRADA SANTA RITA) | G90: =G91+G97+G111 -> 1507385.8
A91: 05.02.01 | C91: OBRAS PRELIMINARES | G91: =SUM(G92:G96) -> 62816.07
A92: 05.02.01.01 | B92: PQ.08.202 | C92: LIMPIEZA INICIAL DEL TERRENO CON EQUIPO | D92: m2 | E92: 2484.84 | F92: 2.95 | G92: =ROUND(E92*F92,2) -> 7330.28
A93: 05.02.01.02 | B93: PQ.08.202 | C93: ELIMINACIÓN DE RESIDUOS SÓLIDOS | D93: m3 | E93: 372.73 | F93: 129.67 | G93: =ROUND(E93*F93,2) -> 48331.9
A94: 05.02.01.03 | B94: PQ.08.202 | C94: TRAZO Y REPLANTEO PARA ESTRUCTURAS | D94: m2 | E94: 940.36 | F94: 3.93 | G94: =ROUND(E94*F94,2) -> 3695.61
A95: 05.02.01.04 | B95: PQ.08.202 | C95: CINTA PLASTICA SENALIZADORA PARA LIMITE DE SEGURIDAD DE OBRA | D95: m | E95: 382.13 | F95: 1.35 | G95: =ROUND(E95*F95,2) -> 515.88
A96: 05.02.01.05 | B96: PQ.08.202 | C96: CERCO DE MALLA HDPE DE 1M DE ALTURA PARA LIMITE DE SEGURIDAD DE OBRA | D96: m | E96: 382.13 | F96: 7.7 | G96: =ROUND(E96*F96,2) -> 2942.4
A97: 05.02.02 | C97: MOVIMIENTO DE TIERRAS | G97: =SUM(G98:G110) -> 723069.53
A98: 05.02.02.01 | B98: PQ.08.202 | C98: EXCAVACION C/MAQ. EN TERRENO NORMAL H<=2M | D98: m3 | E98: 5786.33 | F98: 49.92 | G98: =ROUND(E98*F98,2) -> 288853.59
A99: 05.02.02.02 | B99: PQ.08.202 | C99: EXCAVACION MANUAL PARA ANCLAJE DE GEOTEXTIL | D99: m3 | E99: 12.96 | F99: 44.56 | G99: =ROUND(E99*F99,2) -> 577.5
A100: 05.02.02.03 | B100: PQ.08.202 | C100: CONFORMACIÓN, NIVELACIÓN Y COMPACTACIÓN DE FONDO DE EXCAVACION PARA ESTRUCTURAS | D100: m2 | E100: 963.03 | F100: 10.11 | G100: =ROUND(E100*F100,2) -> 9736.23
A101: 05.02.02.04 | B101: PQ.08.202 | C101: SUMINISTRO EN PUNTO DE ACOPIO DE MATERIAL DE PRÉSTAMO (RELLENO ESTRUCTURAL) | D101: m3 | E101: 1470.5 | F101: 96.78 | G101: =ROUND(E101*F101,2) -> 142314.99
A102: 05.02.02.05 | B102: PQ.08.202 | C102: SUMINISTRO EN PUNTO DE ACOPIO DE PIEDRA CANTO RODADO DE 6" A 10" | D102: m3 | E102: 656.4 | F102: 81.79 | G102: =ROUND(E102*F102,2) -> 53686.96
A103: 05.02.02.06 | B103: PQ.08.202 | C103: RELLENO COMPACTADO PARA ESTRUCTURAS | D103: m3 | E103: 1470.5 | F103: 85.96 | G103: =ROUND(E103*F103,2) -> 126404.18
A104: 05.02.02.07 | B104: PQ.08.202 | C104: TRANSPORTE DE PIEDRA PARA GAVIÓN, D<= 1 KM | D104: m3-km | E104: 577.63 | F104: 8.82 | G104: =ROUND(E104*F104,2) -> 5094.7
A105: 05.02.02.08 | B105: PQ.08.202 | C105: TRANSPORTE DE PIEDRA PARA GAVIÓN, D>1 KM | D105: m3-km | E105: 2298.77 | F105: 1.96 | G105: =ROUND(E105*F105,2) -> 4505.59
A106: 05.02.02.09 | B106: PQ.08.202 | C106: TRANSPORTE DE MATERIAL GRANULAR, D<=1KM | D106: m3-km | E106: 1294.04 | F106: 8.06 | G106: =ROUND(E106*F106,2) -> 10429.96
A107: 05.02.02.10 | B107: PQ.08.202 | C107: TRANSPORTE DE MATERIAL GRANULAR, D>1KM | D107: m3-km | E107: 5848.88 | F107: 1.68 | G107: =ROUND(E107*F107,2) -> 9826.12
A108: 05.02.02.11 | B108: PQ.08.202 | C108: TRANSPORTE DE MATERIAL DE ELIMINACION D<=1KM | D108: m3-km | E108: 2374.68 | F108: 8.82 | G108: =ROUND(E108*F108,2) -> 20944.68
A109: 05.02.02.12 | B109: PQ.08.202 | C109: TRANSPORTE DE MATERIAL DE ELIMINACION D>1KM | D109: m3-km | E109: 1051.97 | F109: 1.96 | G109: =ROUND(E109*F109,2) -> 2061.86
A110: 05.02.02.13 | B110: PQ.08.202 | C110: ENCAUZAMIENTO DE LECHO DE QUEBRADA | D110: m3 | E110: 3087.82 | F110: 15.75 | G110: =ROUND(E110*F110,2) -> 48633.17
A111: 05.02.03 | C111: OBRAS CIVILES | G111: =SUM(G112:G138) -> 721500.18
A112: 05.02.03.01 | B112: PQ.08.202 | C112: SOLADO DE CONCRETO PREMEZCLADO F'C=140 kg/cm2 (CEMENTO TIPO MS), E=0.10m | D112: m2 | E112: 404.53 | F112: 60.28 | G112: =ROUND(E112*F112,2) -> 24385.07
...

Sheet CAOP
C2: CALENDARIO DE AVANCE DE OBRA PORCENTUAL DEL PAQUETE 08
C4: “CONSTRUCCIÓN DEL SISTEMA DE DRENAJE URBANO EN EL SECTOR JESÚS MARÍA – CANAL Y OBRAS DE ESTABILIZACIÓN EN LAS LADERAS DEL SECTOR JESÚS MARÍA (PAQUETE 08)”
B7: =+C2 -> CALENDARIO DE AVANCE DE OBRA PORCENTUAL DEL PAQUETE 08
B8: ÍTEM | C8: DESCRIPCIÓN | D8: 1 | E8: 2 | F8: 3 | G8: 4 | H8: 5 | I8: 6 | J8: 7 | K8: 8 | L8: 9 | M8: 10 | N8: TOTAL
D9: (S/) | E9: (S/) | F9: (S/) | G9: (S/) | H9: (S/) | I9: (S/) | J9: (S/) | K9: (S/) | L9: (S/) | M9: (S/)
B10: 01 | C10: OBRAS PROVISIONALES | D10: =PPTO!#REF!/PPTO!G3 -> #REF! | E10: =PPTO!#REF!/PPTO!G3 -> #REF! | F10: =PPTO!#REF!/PPTO!G3 -> #REF! | G10: =PPTO!#REF!/PPTO!G3 -> #REF! | H10: =PPTO!#REF!/PPTO!G3 -> #REF! | I10: =PPTO!#REF!/PPTO!G3 -> #REF! | J10: =PPTO!#REF!/PPTO!G3 -> #REF! | K10: =PPTO!#REF!/PPTO!G3 -> #REF! | L10: =PPTO!#REF!/PPTO!G3 -> #REF! | M10: =PPTO!#REF!/PPTO!G3 -> #REF! | N10: =SUM(D10:M10) -> #REF!
B11: 01.01 | C11: MOVILIZACION Y DESMOVILIZACION DE EQUIPOS Y/O MAQUINARIAS PAQ-8 | D11: =PPTO!#REF!/PPTO!G4 -> #REF! | E11: =PPTO!#REF!/PPTO!G4 -> #REF! | F11: =PPTO!#REF!/PPTO!G4 -> #REF! | G11: =PPTO!#REF!/PPTO!G4 -> #REF! | H11: =PPTO!#REF!/PPTO!G4 -> #REF! | I11: =PPTO!#REF!/PPTO!G4 -> #REF! | J11: =PPTO!#REF!/PPTO!G4 -> #REF! | K11: =PPTO!#REF!/PPTO!G4 -> #REF! | L11: =PPTO!#REF!/PPTO!G4 -> #REF! | M11: =PPTO!#REF!/PPTO!G4 -> #REF! | N11: =SUM(D11:M11) -> #REF!
B12: 01.02 | C12: CARTEL DE IDENTIFICACION DE LA OBRA DE 3.60 X 2.40 M | D12: =PPTO!#REF!/PPTO!G5 -> #REF! | E12: =PPTO!#REF!/PPTO!G5 -> #REF! | F12: =PPTO!#REF!/PPTO!G5 -> #REF! | G12: =PPTO!#REF!/PPTO!G5 -> #REF! | H12: =PPTO!#REF!/PPTO!G5 -> #REF! | I12: =PPTO!#REF!/PPTO!G5 -> #REF! | J12: =PPTO!#REF!/PPTO!G5 -> #REF! | K12: =PPTO!#REF!/PPTO!G5 -> #REF! | L12: =PPTO!#REF!/PPTO!G5 -> #REF! | M12: =PPTO!#REF!/PPTO!G5 -> #REF! | N12: =SUM(D12:M12) -> #REF!
B13: 01.03 | C13: IMPLEMENTACIÓN DEL PLAN DE GESTION DE TRÁFICO VEHICULAR (PAQ-8) | D13: =PPTO!#REF!/PPTO!G6 -> #REF! | E13: =PPTO!#REF!/PPTO!G6 -> #REF! | F13: =PPTO!#REF!/PPTO!G6 -> #REF! | G13: =PPTO!#REF!/PPTO!G6 -> #REF! | H13: =PPTO!#REF!/PPTO!G6 -> #REF! | I13: =PPTO!#REF!/PPTO!G6 -> #REF! | J13: =PPTO!#REF!/PPTO!G6 -> #REF! | K13: =PPTO!#REF!/PPTO!G6 -> #REF! | L13: =PPTO!#REF!/PPTO!G6 -> #REF! | M13: =PPTO!#REF!/PPTO!G6 -> #REF! | N13: =SUM(D13:M13) -> #REF!
B14: 01.04 | C14: PLAN DE SALUD, SEGURIDAD Y MEDIO AMBIENTE PAQ-8 | D14: =PPTO!#REF!/PPTO!G7 -> #REF! | E14: =PPTO!#REF!/PPTO!G7 -> #REF! | F14: =PPTO!#REF!/PPTO!G7 -> #REF! | G14: =PPTO!#REF!/PPTO!G7 -> #REF! | H14: =PPTO!#REF!/PPTO!G7 -> #REF! | I14: =PPTO!#REF!/PPTO!G7 -> #REF! | J14: =PPTO!#REF!/PPTO!G7 -> #REF! | K14: =PPTO!#REF!/PPTO!G7 -> #REF! | L14: =PPTO!#REF!/PPTO!G7 -> #REF! | M14: =PPTO!#REF!/PPTO!G7 -> #REF! | N14: =SUM(D14:M14) -> #REF!
B15: 01.05 | C15: PLAN DE MANEJO AMBIENTAL PAQ-8 | D15: =PPTO!#REF!/PPTO!G8 -> #REF! | E15: =PPTO!#REF!/PPTO!G8 -> #REF! | F15: =PPTO!#REF!/PPTO!G8 -> #REF! | G15: =PPTO!#REF!/PPTO!G8 -> #REF! | H15: =PPTO!#REF!/PPTO!G8 -> #REF! | I15: =PPTO!#REF!/PPTO!G8 -> #REF! | J15: =PPTO!#REF!/PPTO!G8 -> #REF! | K15: =PPTO!#REF!/PPTO!G8 -> #REF! | L15: =PPTO!#REF!/PPTO!G8 -> #REF! | M15: =PPTO!#REF!/PPTO!G8 -> #REF! | N15: =SUM(D15:M15) -> #REF!
B16: 01.06 | C16: PLAN DE CONTROL CONTRA EL COVID-19 PAQ-8 | D16: =PPTO!#REF!/PPTO!G9 -> #REF! | E16: =PPTO!#REF!/PPTO!G9 -> #REF! | F16: =PPTO!#REF!/PPTO!G9 -> #REF! | G16: =PPTO!#REF!/PPTO!G9 -> #REF! | H16: =PPTO!#REF!/PPTO!G9 -> #REF! | I16: =PPTO!#REF!/PPTO!G9 -> #REF! | J16: =PPTO!#REF!/PPTO!G9 -> #REF! | K16: =PPTO!#REF!/PPTO!G9 -> #REF! | L16: =PPTO!#REF!/PPTO!G9 -> #REF! | M16: =PPTO!#REF!/PPTO!G9 -> #REF! | N16: =SUM(D16:M16) -> #REF!
B17: 01.07 | C17: PLAN DE MANEJO DE AGUAS PLUVIALES Y SUPERFICIALES (PAQ-08) | D17: =PPTO!#REF!/PPTO!G10 -> #REF! | E17: =PPTO!#REF!/PPTO!G10 -> #REF! | F17: =PPTO!#REF!/PPTO!G10 -> #REF! | G17: =PPTO!#REF!/PPTO!G10 -> #REF! | H17: =PPTO!#REF!/PPTO!G10 -> #REF! | I17: =PPTO!#REF!/PPTO!G10 -> #REF! | J17: =PPTO!#REF!/PPTO!G10 -> #REF! | K17: =PPTO!#REF!/PPTO!G10 -> #REF! | L17: =PPTO!#REF!/PPTO!G10 -> #REF! | M17: =PPTO!#REF!/PPTO!G10 -> #REF! | N17: =SUM(D17:M17) -> #REF!
B18: 02 | C18: CAMPAMENTO DE OBRA - YALE 3 | D18: =PPTO!#REF!/PPTO!G11 -> #REF! | E18: =PPTO!#REF!/PPTO!G11 -> #REF! | F18: =PPTO!#REF!/PPTO!G11 -> #REF! | G18: =PPTO!#REF!/PPTO!G11 -> #REF! | H18: =PPTO!#REF!/PPTO!G11 -> #REF! | I18: =PPTO!#REF!/PPTO!G11 -> #REF! | J18: =PPTO!#REF!/PPTO!G11 -> #REF! | K18: =PPTO!#REF!/PPTO!G11 -> #REF! | L18: =PPTO!#REF!/PPTO!G11 -> #REF! | M18: =PPTO!#REF!/PPTO!G11 -> #REF! | N18: =SUM(D18:M18) -> #REF!
B19: 02.01 | C19: TRAZO Y REPLANTEO | D19: =PPTO!#REF!/PPTO!G12 -> #REF! | E19: =PPTO!#REF!/PPTO!G12 -> #REF! | F19: =PPTO!#REF!/PPTO!G12 -> #REF! | G19: =PPTO!#REF!/PPTO!G12 -> #REF! | H19: =PPTO!#REF!/PPTO!G12 -> #REF! | I19: =PPTO!#REF!/PPTO!G12 -> #REF! | J19: =PPTO!#REF!/PPTO!G12 -> #REF! | K19: =PPTO!#REF!/PPTO!G12 -> #REF! | L19: =PPTO!#REF!/PPTO!G12 -> #REF! | M19: =PPTO!#REF!/PPTO!G12 -> #REF! | N19: =SUM(D19:M19) -> #REF!
B20: 02.02 | C20: PERFILADO Y COMPACTADO PARA CAMPAMENTO | D20: =PPTO!#REF!/PPTO!G13 -> #REF! | E20: =PPTO!#REF!/PPTO!G13 -> #REF! | F20: =PPTO!#REF!/PPTO!G13 -> #REF! | G20: =PPTO!#REF!/PPTO!G13 -> #REF! | H20: =PPTO!#REF!/PPTO!G13 -> #REF! | I20: =PPTO!#REF!/PPTO!G13 -> #REF! | J20: =PPTO!#REF!/PPTO!G13 -> #REF! | K20: =PPTO!#REF!/PPTO!G13 -> #REF! | L20: =PPTO!#REF!/PPTO!G13 -> #REF! | M20: =PPTO!#REF!/PPTO!G13 -> #REF! | N20: =SUM(D20:M20) -> #REF!
B21: 02.03 | C21: TRANSPORTE DE MATERIAL GRANULAR, D<=1 KM | D21: =PPTO!#REF!/PPTO!G14 -> #REF! | E21: =PPTO!#REF!/PPTO!G14 -> #REF! | F21: =PPTO!#REF!/PPTO!G14 -> #REF! | G21: =PPTO!#REF!/PPTO!G14 -> #REF! | H21: =PPTO!#REF!/PPTO!G14 -> #REF! | I21: =PPTO!#REF!/PPTO!G14 -> #REF! | J21: =PPTO!#REF!/PPTO!G14 -> #REF! | K21: =PPTO!#REF!/PPTO!G14 -> #REF! | L21: =PPTO!#REF!/PPTO!G14 -> #REF! | M21: =PPTO!#REF!/PPTO!G14 -> #REF! | N21: =SUM(D21:M21) -> #REF!
... B1507: 07.02.01.01 | C1507: DISPOSICIÓN Y CONFORMACIÓN DEL MATERIAL EXCEDENTE (DME) | D1507: =PPTO!#REF!/PPTO!G1500 -> #REF! | E1507: =PPTO!#REF!/PPTO!G1500 -> #REF! | F1507: =PPTO!#REF!/PPTO!G1500 -> #REF! | G1507: =PPTO!#REF!/PPTO!G1500 -> #REF! | H1507: =PPTO!#REF!/PPTO!G1500 -> #REF! | I1507: =PPTO!#REF!/PPTO!G1500 -> #REF! | J1507: =PPTO!#REF!/PPTO!G1500 -> #REF! | K1507: =PPTO!#REF!/PPTO!G1500 -> #REF! | L1507: =PPTO!#REF!/PPTO!G1500 -> #REF! | M1507: =PPTO!#REF!/PPTO!G1500 -> #REF! | N1507: =SUM(D1507:M1507) -> #REF!

Sheet CAOF
C2: CALENDARIO DE AVANCE DE OBRA FISICO DEL PAQUETE 08
C4: “CONSTRUCCIÓN DEL SISTEMA DE DRENAJE URBANO EN EL SECTOR JESÚS MARÍA – CANAL Y OBRAS DE ESTABILIZACIÓN EN LAS LADERAS DEL SECTOR JESÚS MARÍA (PAQUETE 08)”
B7: =+C2 -> CALENDARIO DE AVANCE DE OBRA FISICO DEL PAQUETE 08
B8: ÍTEM | C8: DESCRIPCIÓN | D8: UND. | E8: METRADO | F8: 1 | G8: 2 | H8: 3 | I8: 4 | J8: 5 | K8: 6 | L8: 7 | M8: 8 | N8: 9 | O8: 10
F9: (S/) | G9: (S/) | H9: (S/) | I9: (S/) | J9: (S/) | K9: (S/) | L9: (S/) | M9: (S/) | N9: (S/) | O9: (S/)
B10: 01 | C10: OBRAS PROVISIONALES | Q10: =SUM(F10:O10) -> 0 | R10: =E10-Q10 -> 0
B11: 01.01 | C11: MOVILIZACION Y DESMOVILIZACION DE EQUIPOS Y/O MAQUINARIAS PAQ-8 | D11: glb | E11: 1 | F11: =E11*CAOP!D11 -> #REF! | G11: =E11*CAOP!E11 -> #REF! | H11: =E11*CAOP!F11 -> #REF! | I11: =E11*CAOP!G11 -> #REF! | J11: =E11*CAOP!H11 -> #REF! | K11: =E11*CAOP!I11 -> #REF! | L11: =E11*CAOP!J11 -> #REF! | M11: =E11*CAOP!K11 -> #REF! | N11: =E11*CAOP!L11 -> #REF! | O11: =E11*CAOP!M11 -> #REF! | Q11: =SUM(F11:O11) -> #REF! | R11: =E11-Q11 -> #REF!
B12: 01.02 | C12: CARTEL DE IDENTIFICACION DE LA OBRA DE 3.60 X 2.40 M | D12: und | E12: 2 | F12: =E12*CAOP!D12 -> #REF! | G12: =E12*CAOP!E12 -> #REF! | H12: =E12*CAOP!F12 -> #REF! | I12: =E12*CAOP!G12 -> #REF! | J12: =E12*CAOP!H12 -> #REF! | K12: =E12*CAOP!I12 -> #REF! | L12: =E12*CAOP!J12 -> #REF! | M12: =E12*CAOP!K12 -> #REF! | N12: =E12*CAOP!L12 -> #REF! | O12: =E12*CAOP!M12 -> #REF! | Q12: =SUM(F12:O12) -> #REF! | R12: =E12-Q12 -> #REF!
B13: 01.03 | C13: IMPLEMENTACIÓN DEL PLAN DE GESTION DE TRÁFICO VEHICULAR (PAQ-8) | D13: mes | E13: 11 | F13: =E13*CAOP!D13 -> #REF! | G13: =E13*CAOP!E13 -> #REF! | H13: =E13*CAOP!F13 -> #REF! | I13: =E13*CAOP!G13 -> #REF! | J13: =E13*CAOP!H13 -> #REF! | K13: =E13*CAOP!I13 -> #REF! | L13: =E13*CAOP!J13 -> #REF! | M13: =E13*CAOP!K13 -> #REF! | N13: =E13*CAOP!L13 -> #REF! | O13: =E13*CAOP!M13 -> #REF! | Q13: =SUM(F13:O13) -> #REF! | R13: =E13-Q13 -> #REF!
B14: 01.04 | C14: PLAN DE SALUD, SEGURIDAD Y MEDIO AMBIENTE PAQ-8 | D14: glb | E14: 1 | F14: =E14*CAOP!D14 -> #REF! | G14: =E14*CAOP!E14 -> #REF! | H14: =E14*CAOP!F14 -> #REF! | I14: =E14*CAOP!G14 -> #REF! | J14: =E14*CAOP!H14 -> #REF! | K14: =E14*CAOP!I14 -> #REF! | L14: =E14*CAOP!J14 -> #REF! | M14: =E14*CAOP!K14 -> #REF! | N14: =E14*CAOP!L14 -> #REF! | O14: =E14*CAOP!M14 -> #REF! | Q14: =SUM(F14:O14) -> #REF! | R14: =E14-Q14 -> #REF!
B15: 01.05 | C15: PLAN DE MANEJO AMBIENTAL PAQ-8 | D15: glb | E15: 1 | F15: =E15*CAOP!D15 -> #REF! | G15: =E15*CAOP!E15 -> #REF! | H15: =E15*CAOP!F15 -> #REF! | I15: =E15*CAOP!G15 -> #REF! | J15: =E15*CAOP!H15 -> #REF! | K15: =E15*CAOP!I15 -> #REF! | L15: =E15*CAOP!J15 -> #REF! | M15: =E15*CAOP!K15 -> #REF! | N15: =E15*CAOP!L15 -> #REF! | O15: =E15*CAOP!M15 -> #REF! | Q15: =SUM(F15:O15) -> #REF! | R15: =E15-Q15 -> #REF!
B16: 01.06 | C16: PLAN DE CONTROL CONTRA EL COVID-19 PAQ-8 | D16: glb | E16: 1 | F16: =E16*CAOP!D16 -> #REF! | G16: =E16*CAOP!E16 -> #REF! | H16: =E16*CAOP!F16 -> #REF! | I16: =E16*CAOP!G16 -> #REF! | J16: =E16*CAOP!H16 -> #REF! | K16: =E16*CAOP!I16 -> #REF! | L16: =E16*CAOP!J16 -> #REF! | M16: =E16*CAOP!K16 -> #REF! | N16: =E16*CAOP!L16 -> #REF! | O16: =E16*CAOP!M16 -> #REF! | Q16: =SUM(F16:O16) -> #REF! | R16: =E16-Q16 -> #REF!
B17: 01.07 | C17: PLAN DE MANEJO DE AGUAS PLUVIALES Y SUPERFICIALES (PAQ-08) | D17: glb | E17: 1 | F17: =E17*CAOP!D17 -> #REF! | G17: =E17*CAOP!E17 -> #REF! | H17: =E17*CAOP!F17 -> #REF! | I17: =E17*CAOP!G17 -> #REF! | J17: =E17*CAOP!H17 -> #REF! | K17: =E17*CAOP!I17 -> #REF! | L17: =E17*CAOP!J17 -> #REF! | M17: =E17*CAOP!K17 -> #REF! | N17: =E17*CAOP!L17 -> #REF! | O17: =E17*CAOP!M17 -> #REF! | Q17: =SUM(F17:O17) -> #REF! | R17: =E17-Q17 -> #REF!
B18: 02 | C18: CAMPAMENTO DE OBRA - YALE 3 | Q18: =SUM(F18:O18) -> 0 | R18: =E18-Q18 -> 0
B19: 02.01 | C19: TRAZO Y REPLANTEO | D19: m2 | E19: 9490 | F19: =E19*CAOP!D19 -> #REF! | G19: =E19*CAOP!E19 -> #REF! | H19: =E19*CAOP!F19 -> #REF! | I19: =E19*CAOP!G19 -> #REF! | J19: =E19*CAOP!H19 -> #REF! | K19: =E19*CAOP!I19 -> #REF! | L19: =E19*CAOP!J19 -> #REF! | M19: =E19*CAOP!K19 -> #REF! | N19: =E19*CAOP!L19 -> #REF! | O19: =E19*CAOP!M19 -> #REF! | Q19: =SUM(F19:O19) -> #REF! | R19: =E19-Q19 -> #REF!
B20: 02.02 | C20: PERFILADO Y COMPACTADO PARA CAMPAMENTO | D20: m2 | E20: 9490 | F20: =E20*CAOP!D20 -> #REF! | G20: =E20*CAOP!E20 -> #REF! | H20: =E20*CAOP!F20 -> #REF! | I20: =E20*CAOP!G20 -> #REF! | J20: =E20*CAOP!H20 -> #REF! | K20: =E20*CAOP!I20 -> #REF! | L20: =E20*CAOP!J20 -> #REF! | M20: =E20*CAOP!K20 -> #REF! | N20: =E20*CAOP!L20 -> #REF! | O20: =E20*CAOP!M20 -> #REF! | Q20: =SUM(F20:O20) -> #REF! | R20: =E20-Q20 -> #REF!
B21: 02.03 | C21: TRANSPORTE DE MATERIAL GRANULAR, D<=1 KM | D21: m3-km | E21: 1898 | F21: =E21*CAOP!D21 -> #REF! | G21: =E21*CAOP!E21 -> #REF! | H21: =E21*CAOP!F21 -> #REF! | I21: =E21*CAOP!G21 -> #REF! | J21: =E21*CAOP!H21 -> #REF! | K21: =E21*CAOP!I21 -> #REF! | L21: =E21*CAOP!J21 -> #REF! | M21: =E21*CAOP!K21 -> #REF! | N21: =E21*CAOP!L21 -> #REF! | O21: =E21*CAOP!M21 -> #REF! | Q21: =SUM(F21:O21) -> #REF! | R21: =E21-Q21 -> #REF!
B22: 02.04 | C22: SUMINISTRO EN PUNTO DE ACOPIO DE MATERIAL DE PRÉSTAMO (AFIRMADO) | D22: m3 | E22: 1898 | F22: =E22*CAOP!D22 -> #REF! | G22: =E22*CAOP!E22 -> #REF! | H22: =E22*CAOP!F22 -> #REF! | I22: =E22*CAOP!G22 -> #REF! | J22: =E22*CAOP!H22 -> #REF! | K22: =E22*CAOP!I22 -> #REF! | L22: =E22*CAOP!J22 -> #REF! | M22: =E22*CAOP!K22 -> #REF! | N22: =E22*CAOP!L22 -> #REF! | O22: =E22*CAOP!M22 -> #REF! | Q22: =SUM(F22:O22) -> #REF! | R22: =E22-Q22 -> #REF!
B23: 02.05 | C23: CONFORMACIÓN DE TERRENO CON MATERIAL DE AFIRMADO | D23: m3 | E23: 1898 | F23: =E23*CAOP!D23 -> #REF! | G23: =E23*CAOP!E23 -> #REF! | H23: =E23*CAOP!F23 -> #REF! | I23: =E23*CAOP!G23 -> #REF! | J23: =E23*CAOP!H23 -> #REF! | K23: =E23*CAOP!I23 -> #REF! | L23: =E23*CAOP!J23 -> #REF! | M23: =E23*CAOP!K23 -> #REF! | N23: =E23*CAOP!L23 -> #REF! | O23: =E23*CAOP!M23 -> #REF! | Q23: =SUM(F23:O23) -> #REF! | R23: =E23-Q23 -> #REF!
B24: 02.06 | C24: CONFORMACION Y COMPACTACION CON MATERAIL PROPIO | D24: m3 | E24: 2035.2 | F24: =E24*CAOP!D24 -> #REF! | G24: =E24*CAOP!E24 -> #REF! | H24: =E24*CAOP!F24 -> #REF! | I24: =E24*CAOP!G24 -> #REF! | J24: =E24*CAOP!H24 -> #REF! | K24: =E24*CAOP!I24 -> #REF! | L24: =E24*CAOP!J24 -> #REF! | M24: =E24*CAOP!K24 -> #REF! | N24: =E24*CAOP!L24 -> #REF! | O24: =E24*CAOP!M24 -> #REF! | Q24: =SUM(F24:O24) -> #REF! | R24: =E24-Q24 -> #REF!
B25: 02.07 | C25: CERCO DE CAMPAMENTO | D25: m | E25: 396 | F25: =E25*CAOP!D25 -> #REF! | G25: =E25*CAOP!E25 -> #REF! | H25: =E25*CAOP!F25 -> #REF! | I25: =E25*CAOP!G25 -> #REF! | J25: =E25*CAOP!H25 -> #REF! | K25: =E25*CAOP!I25 -> #REF! | L25: =E25*CAOP!J25 -> #REF! | M25: =E25*CAOP!K25 -> #REF! | N25: =E25*CAOP!L25 -> #REF! | O25: =E25*CAOP!M25 -> #REF! | Q25: =SUM(F25:O25) -> #REF! | R25: =E25-Q25 -> #REF!
B26: 02.08 | C26: PORTON CAMPAMENTO | D26: und | E26: 1 | F26: =E26*CAOP!D26 -> #REF! | G26: =E26*CAOP!E26 -> #REF! | H26: =E26*CAOP!F26 -> #REF! | I26: =E26*CAOP!G26 -> #REF! | J26: =E26*CAOP!H26 -> #REF! | K26: =E26*CAOP!I26 -> #REF! | L26: =E26*CAOP!J26 -> #REF! | M26: =E26*CAOP!K26 -> #REF! | N26: =E26*CAOP!L26 -> #REF! | O26: =E26*CAOP!M26 -> #REF! | Q26: =SUM(F26:O26) -> #REF! | R26: =E26-Q26 -> #REF!
B27: 02.09 | C27: GRUPO ELECTROGENO | D27: mes | E27: 11 | F27: =E27*CAOP!D27 -> #REF! | G27: =E27*CAOP!E27 -> #REF! | H27: =E27*CAOP!F27 -> #REF! | I27: =E27*CAOP!G27 -> #REF! | J27: =E27*CAOP!H27 -> #REF! | K27: =E27*CAOP!I27 -> #REF! | L27: =E27*CAOP!J27 -> #REF! | M27: =E27*CAOP!K27 -> #REF! | N27: =E27*CAOP!L27 -> #REF! | O27: =E27*CAOP!M27 -> #REF! | Q27: =SUM(F27:O27) -> #REF! | R27: =E27-Q27 -> #REF!
B28: 02.10 | C28: SERVICIO DE INTERNET | D28: mes | E28: 11 | F28: =E28*CAOP!D28 -> #REF! | G28: =E28*CAOP!E28 -> #REF! | H28: =E28*CAOP!F28 -> #REF! | I28: =E28*CAOP!G28 -> #REF! | J28: =E28*CAOP!H28 -> #REF! | K28: =E28*CAOP!I28 -> #REF! | L28: =E28*CAOP!J28 -> #REF! | M28: =E28*CAOP!K28 -> #REF! | N28: =E28*CAOP!L28 -> #REF! | O28: =E28*CAOP!M28 -> #REF! | Q28: =SUM(F28:O28) -> #REF! | R28: =E28-Q28 -> #REF!
B29: 02.11 | C29: SERVICIO DE LIMPIEZA DE OFICINA | D29: mes | E29: 11 | F29: =E29*CAOP!D29 -> #REF! | G29: =E29*CAOP!E29 -> #REF! | H29: =E29*CAOP!F29 -> #REF! | I29: =E29*CAOP!G29 -> #REF! | J29: =E29*CAOP!H29 -> #REF! | K29: =E29*CAOP!I29 -> #REF! | L29: =E29*CAOP!J29 -> #REF! | M29: =E29*CAOP!K29 -> #REF! | N29: =E29*CAOP!L29 -> #REF! | O29: =E29*CAOP!M29 -> #REF! | Q29: =SUM(F29:O29) -> #REF! | R29: =E29-Q29 -> #REF!
B30: 02.12 | C30: SERVICIO DE SEGURIDAD DE OFICINA | D30: mes | E30: 11 | F30: =E30*CAOP!D30 -> #REF! | G30: =E30*CAOP!E30 -> #REF! | H30: =E30*CAOP!F30 -> #REF! | I30: =E30*CAOP!G30 -> #REF! | J30: =E30*CAOP!H30 -> #REF! | K30: =E30*CAOP!I30 -> #REF! | L30: =E30*CAOP!J30 -> #REF! | M30: =E30*CAOP!K30 -> #REF! | N30: =E30*CAOP!L30 -> #REF! | O30: =E30*CAOP!M30 -> #REF! | Q30: =SUM(F30:O30) -> #REF! | R30: =E30-Q30 -> #REF!
... B42: 02.24 | C42: AREA DE LABORATORIO DE SUELOS, PAVIMENTOS Y CONCRETO | D42: m2 | E42: 35 | F42: =E42*CAOP!D42 -> #REF! | G42: =E42*CAOP!E42 -> #REF! | H42: =E42*CAOP!F42 -> #REF! | I42: =E42*CAOP!G42 -> #REF! | J42: =E42*CAOP!H42 -> #REF! | K42: =E42*CAOP!I42 -> #REF! | L42: =E42*CAOP!J42 -> #REF! | M42: =E42*CAOP!K42 -> #REF! | N42: =E42*CAOP!L42 -> #REF! | O42: =E42*CAOP!M42 -> #REF! | Q42: =SUM(F42:O42) -> #REF! | R42: =E42-Q42 -> #REF!
B43: 03 | C43: HABILITACION DE PUNTO DE ACOPIO - YALE 3 | Q43: =SUM(F43:O43) -> 0 | R43: =E43-Q43 -> 0
B44: 03.01 | C44: TRAZO Y REPLANTEO | D44: m2 | E44: 17160 | F44: =E44*CAOP!D44 -> #REF! | G44: =E44*CAOP!E44 -> #REF! | H44: =E44*CAOP!F44 -> #REF! | I44: =E44*CAOP!G44 -> #REF! | J44: =E44*CAOP!H44 -> #REF! | K44: =E44*CAOP!I44 -> #REF! | L44: =E44*CAOP!J44 -> #REF! | M44: =E44*CAOP!K44 -> #REF! | N44: =E44*CAOP!L44 -> #REF! | O44: =E44*CAOP!M44 -> #REF! | Q44: =SUM(F44:O44) -> #REF! | R44: =E44-Q44 -> #REF!
B45: 03.02 | C45: PERFILADO Y COMPACTADO PARA PUNTO DE ACOPIO | D45: m2 | E45: 17160 | F45: =E45*CAOP!D45 -> #REF! | G45: =E45*CAOP!E45 -> #REF! | H45: =E45*CAOP!F45 -> #REF! | I45: =E45*CAOP!G45 -> #REF! | J45: =E45*CAOP!H45 -> #REF! | K45: =E45*CAOP!I45 -> #REF! | L45: =E45*CAOP!J45 -> #REF! | M45: =E45*CAOP!K45 -> #REF! | N45: =E45*CAOP!L45 -> #REF! | O45: =E45*CAOP!M45 -> #REF! | Q45: =SUM(F45:O45) -> #REF! | R45: =E45-Q45 -> #REF!
B46: 03.03 | C46: SUMINISTRO EN PUNTO DE ACOPIO DE MATERIAL DE PRÉSTAMO (AFIRMADO) | D46: m3 | E46: 3432 | F46: =E46*CAOP!D46 -> #REF! | G46: =E46*CAOP!E46 -> #REF! | H46: =E46*CAOP!F46 -> #REF! | I46: =E46*CAOP!G46 -> #REF! | J46: =E46*CAOP!H46 -> #REF! | K46: =E46*CAOP!I46 -> #REF! | L46: =E46*CAOP!J46 -> #REF! | M46: =E46*CAOP!K46 -> #REF! | N46: =E46*CAOP!L46 -> #REF! | O46: =E46*CAOP!M46 -> #REF! | Q46: =SUM(F46:O46) -> #REF! | R46: =E46-Q46 -> #REF!
B47: 03.04 | C47: CONFORMACIÓN DE TERRENO CON MATERIAL DE AFIRMADO | D47: m3 | E47: 3432 | F47: =E47*CAOP!D47 -> #REF! | G47: =E47*CAOP!E47 -> #REF! | H47: =E47*CAOP!F47 -> #REF! | I47: =E47*CAOP!G47 -> #REF! | J47: =E47*CAOP!H47 -> #REF! | K47: =E47*CAOP!I47 -> #REF! | L47: =E47*CAOP!J47 -> #REF! | M47: =E47*CAOP!K47 -> #REF! | N47: =E47*CAOP!L47 -> #REF! | O47: =E47*CAOP!M47 -> #REF! | Q47: =SUM(F47:O47) -> #REF! | R47: =E47-Q47 -> #REF!
B48: 03.05 | C48: CERCO PARA PUNTO DE ACOPIO | D48: m | E48: 384 | F48: =E48*CAOP!D48 -> #REF! | G48: =E48*CAOP!E48 -> #REF! | H48: =E48*CAOP!F48 -> #REF! | I48: =E48*CAOP!G48 -> #REF! | J48: =E48*CAOP!H48 -> #REF! | K48: =E48*CAOP!I48 -> #REF! | L48: =E48*CAOP!J48 -> #REF! | M48: =E48*CAOP!K48 -> #REF! | N48: =E48*CAOP!L48 -> #REF! | O48: =E48*CAOP!M48 -> #REF! | Q48: =SUM(F48:O48) -> #REF! | R48: =E48-Q48 -> #REF!
B49: 03.06 | C49: PORTON PUNTO DE ACOPIO | D49: und | E49: 1 | F49: =E49*CAOP!D49 -> #REF! | G49: =E49*CAOP!E49 -> #REF! | H49: =E49*CAOP!F49 -> #REF! | I49: =E49*CAOP!G49 -> #REF! | J49: =E49*CAOP!H49 -> #REF! | K49: =E49*CAOP!I49 -> #REF! | L49: =E49*CAOP!J49 -> #REF! | M49: =E49*CAOP!K49 -> #REF! | N49: =E49*CAOP!L49 -> #REF! | O49: =E49*CAOP!M49 -> #REF! | Q49: =SUM(F49:O49) -> #REF! | R49: =E49-Q49 -> #REF!
B50: 03.07 | C50: CASETA DE GUARDIANÍA | D50: mes | E50: 9 | F50: =E50*CAOP!D50 -> #REF! | G50: =E50*CAOP!E50 -> #REF! | H50: =E50*CAOP!F50 -> #REF! | I50: =E50*CAOP!G50 -> #REF! | J50: =E50*CAOP!H50 -> #REF! | K50: =E50*CAOP!I50 -> #REF! | L50: =E50*CAOP!J50 -> #REF! | M50: =E50*CAOP!K50 -> #REF! | N50: =E50*CAOP!L50 -> #REF! | O50: =E50*CAOP!M50 -> #REF! | Q50: =SUM(F50:O50) -> #REF! | R50: =E50-Q50 -> #REF!
B51: 04 | C51: ACCESO A COMPONENTE 4 - CANAL JESUS MARIA | Q51: =SUM(F51:O51) -> 0 | R51: =E51-Q51 -> 0
B52: 04.01 | C52: ACCESO 01 | Q52: =SUM(F52:O52) -> 0 | R52: =E52-Q52 -> 0
B53: 04.01.01 | C53: TRAZO Y REPLANTEO PARA OBRAS VIALES | D53: km | E53: 1.31 | F53: =E53*CAOP!D53 -> #REF! | G53: =E53*CAOP!E53 -> #REF! | H53: =E53*CAOP!F53 -> #REF! | I53: =E53*CAOP!G53 -> #REF! | J53: =E53*CAOP!H53 -> #REF! | K53: =E53*CAOP!I53 -> #REF! | L53: =E53*CAOP!J53 -> #REF! | M53: =E53*CAOP!K53 -> #REF! | N53: =E53*CAOP!L53 -> #REF! | O53: =E53*CAOP!M53 -> #REF! | Q53: =SUM(F53:O53) -> #REF! | R53: =E53-Q53 -> #REF!
B54: 04.01.02 | C54: EXCAVACION C/MAQ. EN TERRENO NORMAL H<=2M | D54: m3 | E54: 13890.8 | F54: =E54*CAOP!D54 -> #REF! | G54: =E54*CAOP!E54 -> #REF! | H54: =E54*CAOP!F54 -> #REF! | I54: =E54*CAOP!G54 -> #REF! | J54: =E54*CAOP!H54 -> #REF! | K54: =E54*CAOP!I54 -> #REF! | L54: =E54*CAOP!J54 -> #REF! | M54: =E54*CAOP!K54 -> #REF! | N54: =E54*CAOP!L54 -> #REF! | O54: =E54*CAOP!M54 -> #REF! | Q54: =SUM(F54:O54) -> #REF! | R54: =E54-Q54 -> #REF!
B55: 04.01.03 | C55: ACARREO DE MATERIAL PROVENIENTE DE EXCAVACIONES, D<= 1KM | D55: m3-km | E55: 13890.8 | F55: =E55*CAOP!D55 -> #REF! | G55: =E55*CAOP!E55 -> #REF! | H55: =E55*CAOP!F55 -> #REF! | I55: =E55*CAOP!G55 -> #REF! | J55: =E55*CAOP!H55 -> #REF! | K55: =E55*CAOP!I55 -> #REF! | L55: =E55*CAOP!J55 -> #REF! | M55: =E55*CAOP!K55 -> #REF! | N55: =E55*CAOP!L55 -> #REF! | O55: =E55*CAOP!M55 -> #REF! | Q55: =SUM(F55:O55) -> #REF! | R55: =E55-Q55 -> #REF!
B56: 04.01.04 | C56: RELLENO COMPACTADO CON MATERIAL PROPIO | D56: m3 | E56: 4794.07 | F56: =E56*CAOP!D56 -> #REF! | G56: =E56*CAOP!E56 -> #REF! | H56: =E56*CAOP!F56 -> #REF! | I56: =E56*CAOP!G56 -> #REF! | J56: =E56*CAOP!H56 -> #REF! | K56: =E56*CAOP!I56 -> #REF! | L56: =E56*CAOP!J56 -> #REF! | M56: =E56*CAOP!K56 -> #REF! | N56: =E56*CAOP!L56 -> #REF! | O56: =E56*CAOP!M56 -> #REF! | Q56: =SUM(F56:O56) -> #REF! | R56: =E56-Q56 -> #REF!
B57: 04.01.05 | C57: PERFILADO Y COMPACTADO EN ZONAS DE CORTE | D57: m2 | E57: 7680 | F57: =E57*CAOP!D57 -> #REF! | G57: =E57*CAOP!E57 -> #REF! | H57: =E57*CAOP!F57 -> #REF! | I57: =E57*CAOP!G57 -> #REF! | J57: =E57*CAOP!H57 -> #REF! | K57: =E57*CAOP!I57 -> #REF! | L57: =E57*CAOP!J57 -> #REF! | M57: =E57*CAOP!K57 -> #REF! | N57: =E57*CAOP!L57 -> #REF! | O57: =E57*CAOP!M57 -> #REF! | Q57: =SUM(F57:O57) -> #REF! | R57: =E57-Q57 -> #REF!
B58: 04.01.06 | C58: CONFORMACION DE TERRENO CON MATERIAL DE AFIRMADO (E=0.20M) | D58: m3 | E58: 1803.84 | F58: =E58*CAOP!D58 -> #REF! | G58: =E58*CAOP!E58 -> #REF! | H58: =E58*CAOP!F58 -> #REF! | I58: =E58*CAOP!G58 -> #REF! | J58: =E58*CAOP!H58 -> #REF! | K58: =E58*CAOP!I58 -> #REF! | L58: =E58*CAOP!J58 -> #REF! | M58: =E58*CAOP!K58 -> #REF! | N58: =E58*CAOP!L58 -> #REF! | O58: =E58*CAOP!M58 -> #REF! | Q58: =SUM(F58:O58) -> #REF! | R58: =E58-Q58 -> #REF!
B59: 04.01.07 | C59: SUMINISTRO EN PUNTO DE ACOPIO DE MATERIAL DE PRESTAMO (AFIRMADO) | D59: m3 | E59: 1803.84 | F59: =E59*CAOP!D59 -> #REF! | G59: =E59*CAOP!E59 -> #REF! | H59: =E59*CAOP!F59 -> #REF! | I59: =E59*CAOP!G59 -> #REF! | J59: =E59*CAOP!H59 -> #REF! | K59: =E59*CAOP!I59 -> #REF! | L59: =E59*CAOP!J59 -> #REF! | M59: =E59*CAOP!K59 -> #REF! | N59: =E59*CAOP!L59 -> #REF! | O59: =E59*CAOP!M59 -> #REF! | Q59: =SUM(F59:O59) -> #REF! | R59: =E59-Q59 -> #REF!
B60: 04.01.08 | C60: TRANSPORTE DE MATERIAL GRANULAR, D<=1KM | D60: m3-km | E60: 5806.16 | F60: =E60*CAOP!D60 -> #REF! | G60: =E60*CAOP!E60 -> #REF! | H60: =E60*CAOP!F60 -> #REF! | I60: =E60*CAOP!G60 -> #REF! | J60: =E60*CAOP!H60 -> #REF! | K60: =E60*CAOP!I60 -> #REF! | L60: =E60*CAOP!J60 -> #REF! | M60: =E60*CAOP!K60 -> #REF! | N60: =E60*CAOP!L60 -> #REF! | O60: =E60*CAOP!M60 -> #REF! | Q60: =SUM(F60:O60) -> #REF! | R60: =E60-Q60 -> #REF!
B61: 04.01.09 | C61: TRANSPORTE DE MATERIAL GRANULAR, D>1KM | D61: m3-km | E61: 4586.36 | F61: =E61*CAOP!D61 -> #REF! | G61: =E61*CAOP!E61 -> #REF! | H61: =E61*CAOP!F61 -> #REF! | I61: =E61*CAOP!G61 -> #REF! | J61: =E61*CAOP!H61 -> #REF! | K61: =E61*CAOP!I61 -> #REF! | L61: =E61*CAOP!J61 -> #REF! | M61: =E61*CAOP!K61 -> #REF! | N61: =E61*CAOP!L61 -> #REF! | O61: =E61*CAOP!M61 -> #REF! | Q61: =SUM(F61:O61) -> #REF! | R61: =E61-Q61 -> #REF!
B62: 04.01.10 | C62: TRANSPORTE DE MATERIAL DE ELIMINACION D<=1KM | D62: m3-km | E62: 12223.9 | F62: =E62*CAOP!D62 -> #REF! | G62: =E62*CAOP!E62 -> #REF! | H62: =E62*CAOP!F62 -> #REF! | I62: =E62*CAOP!G62 -> #REF! | J62: =E62*CAOP!H62 -> #REF! | K62: =E62*CAOP!I62 -> #REF! | L62: =E62*CAOP!J62 -> #REF! | M62: =E62*CAOP!K62 -> #REF! | N62: =E62*CAOP!L62 -> #REF! | O62: =E62*CAOP!M62 -> #REF! | Q62: =SUM(F62:O62) -> #REF! | R62: =E62-Q62 -> #REF!
B63: 04.01.11 | C63: TRANSPORTE DE MATERIAL DE ELIMINACION D>1KM | D63: m3-km | E63: 56323.67 | F63: =E63*CAOP!D63 -> #REF! | G63: =E63*CAOP!E63 -> #REF! | H63: =E63*CAOP!F63 -> #REF! | I63: =E63*CAOP!G63 -> #REF! | J63: =E63*CAOP!H63 -> #REF! | K63: =E63*CAOP!I63 -> #REF! | L63: =E63*CAOP!J63 -> #REF! | M63: =E63*CAOP!K63 -> #REF! | N63: =E63*CAOP!L63 -> #REF! | O63: =E63*CAOP!M63 -> #REF! | Q63: =SUM(F63:O63) -> #REF! | R63: =E63-Q63 -> #REF!
B64: 04.02 | C64: ACCESO 02 | Q64: =SUM(F64:O64) -> 0 | R64: =E64-Q64 -> 0
B65: 04.02.01 | C65: TRAZO Y REPLANTEO PARA OBRAS VIALES | D65: km | E65: 0.09 | F65: =E65*CAOP!D65 -> #REF! | G65: =E65*CAOP!E65 -> #REF! | H65: =E65*CAOP!F65 -> #REF! | I65: =E65*CAOP!G65 -> #REF! | J65: =E65*CAOP!H65 -> #REF! | K65: =E65*CAOP!I65 -> #REF! | L65: =E65*CAOP!J65 -> #REF! | M65: =E65*CAOP!K65 -> #REF! | N65: =E65*CAOP!L65 -> #REF! | O65: =E65*CAOP!M65 -> #REF! | Q65: =SUM(F65:O65) -> #REF! | R65: =E65-Q65 -> #REF!
B66: 04.02.02 | C66: EXCAVACION C/MAQ. EN TERRENO NORMAL H<=2M | D66: m3 | E66: 705.38 | F66: =E66*CAOP!D66 -> #REF! | G66: =E66*CAOP!E66 -> #REF! | H66: =E66*CAOP!F66 -> #REF! | I66: =E66*CAOP!G66 -> #REF! | J66: =E66*CAOP!H66 -> #REF! | K66: =E66*CAOP!I66 -> #REF! | L66: =E66*CAOP!J66 -> #REF! | M66: =E66*CAOP!K66 -> #REF! | N66: =E66*CAOP!L66 -> #REF! | O66: =E66*CAOP!M66 -> #REF! | Q66: =SUM(F66:O66) -> #REF! | R66: =E66-Q66 -> #REF!
B67: 04.02.03 | C67: ACARREO DE MATERIAL PROVENIENTE DE EXCAVACIONES, D<= 1KM | D67: m3-km | E67: 705.38 | F67: =E67*CAOP!D67 -> #REF! | G67: =E67*CAOP!E67 -> #REF! | H67: =E67*CAOP!F67 -> #REF! | I67: =E67*CAOP!G67 -> #REF! | J67: =E67*CAOP!H67 -> #REF! | K67: =E67*CAOP!I67 -> #REF! | L67: =E67*CAOP!J67 -> #REF! | M67: =E67*CAOP!K67 -> #REF! | N67: =E67*CAOP!L67 -> #REF! | O67: =E67*CAOP!M67 -> #REF! | Q67: =SUM(F67:O67) -> #REF! | R67: =E67-Q67 -> #REF!
B68: 04.02.04 | C68: RELLENO COMPACTADO CON MATERIAL PROPIO | D68: m3 | E68: 166.69 | F68: =E68*CAOP!D68 -> #REF! | G68: =E68*CAOP!E68 -> #REF! | H68: =E68*CAOP!F68 -> #REF! | I68: =E68*CAOP!G68 -> #REF! | J68: =E68*CAOP!H68 -> #REF! | K68: =E68*CAOP!I68 -> #REF! | L68: =E68*CAOP!J68 -> #REF! | M68: =E68*CAOP!K68 -> #REF! | N68: =E68*CAOP!L68 -> #REF! | O68: =E68*CAOP!M68 -> #REF! | Q68: =SUM(F68:O68) -> #REF! | R68: =E68-Q68 -> #REF!
B69: 04.02.05 | C69: PERFILADO Y COMPACTADO EN ZONAS DE CORTE | D69: m2 | E69: 566.46 | F69: =E69*CAOP!D69 -> #REF! | G69: =E69*CAOP!E69 -> #REF! | H69: =E69*CAOP!F69 -> #REF! | I69: =E69*CAOP!G69 -> #REF! | J69: =E69*CAOP!H69 -> #REF! | K69: =E69*CAOP!I69 -> #REF! | L69: =E69*CAOP!J69 -> #REF! | M69: =E69*CAOP!K69 -> #REF! | N69: =E69*CAOP!L69 -> #REF! | O69: =E69*CAOP!M69 -> #REF! | Q69: =SUM(F69:O69) -> #REF! | R69: =E69-Q69 -> #REF!
B70: 04.02.06 | C70: CONFORMACION DE TERRENO CON MATERIAL DE AFIRMADO (E=0.20M) | D70: m3 | E70: 151.66 | F70: =E70*CAOP!D70 -> #REF! | G70: =E70*CAOP!E70 -> #REF! | H70: =E70*CAOP!F70 -> #REF! | I70: =E70*CAOP!G70 -> #REF! | J70: =E70*CAOP!H70 -> #REF! | K70: =E70*CAOP!I70 -> #REF! | L70: =E70*CAOP!J70 -> #REF! | M70: =E70*CAOP!K70 -> #REF! | N70: =E70*CAOP!L70 -> #REF! | O70: =E70*CAOP!M70 -> #REF! | Q70: =SUM(F70:O70) -> #REF! | R70: =E70-Q70 -> #REF!
B71: 04.02.07 | C71: SUMINISTRO EN PUNTO DE ACOPIO DE MATERIAL DE PRESTAMO (AFIRMADO) | D71: m3 | E71: 151.66 | F71: =E71*CAOP!D71 -> #REF! | G71: =E71*CAOP!E71 -> #REF! | H71: =E71*CAOP!F71 -> #REF! | I71: =E71*CAOP!G71 -> #REF! | J71: =E71*CAOP!H71 -> #REF! | K71: =E71*CAOP!I71 -> #REF! | L71: =E71*CAOP!J71 -> #REF! | M71: =E71*CAOP!K71 -> #REF! | N71: =E71*CAOP!L71 -> #REF! | O71: =E71*CAOP!M71 -> #REF! | Q71: =SUM(F71:O71) -> #REF! | R71: =E71-Q71 -> #REF!
B72: 04.02.08 | C72: TRANSPORTE DE MATERIAL GRANULAR, D<=1KM | D72: m3-km | E72: 280.14 | F72: =E72*CAOP!D72 -> #REF! | G72: =E72*CAOP!E72 -> #REF! | H72: =E72*CAOP!F72 -> #REF! | I72: =E72*CAOP!G72 -> #REF! | J72: =E72*CAOP!H72 -> #REF! | K72: =E72*CAOP!I72 -> #REF! | L72: =E72*CAOP!J72 -> #REF! | M72: =E72*CAOP!K72 -> #REF! | N72: =E72*CAOP!L72 -> #REF! | O72: =E72*CAOP!M72 -> #REF! | Q72: =SUM(F72:O72) -> #REF! | R72: =E72-Q72 -> #REF!
B73: 04.02.09 | C73: TRANSPORTE DE MATERIAL GRANULAR, D>1KM | D73: m3-km | E73: 1342.55 | F73: =E73*CAOP!D73 -> #REF! | G73: =E73*CAOP!E73 -> #REF! | H73: =E73*CAOP!F73 -> #REF! | I73: =E73*CAOP!G73 -> #REF! | J73: =E73*CAOP!H73 -> #REF! | K73: =E73*CAOP!I73 -> #REF! | L73: =E73*CAOP!J73 -> #REF! | M73: =E73*CAOP!K73 -> #REF! | N73: =E73*CAOP!L73 -> #REF! | O73: =E73*CAOP!M73 -> #REF! | Q73: =SUM(F73:O73) -> #REF! | R73: =E73-Q73 -> #REF!
B74: 04.02.10 | C74: TRANSPORTE DE MATERIAL DE ELIMINACION D<=1KM | D74: m3-km | E74: 620.73 | F74: =E74*CAOP!D74 -> #REF! | G74: =E74*CAOP!E74 -> #REF! | H74: =E74*CAOP!F74 -> #REF! | I74: =E74*CAOP!G74 -> #REF! | J74: =E74*CAOP!H74 -> #REF! | K74: =E74*CAOP!I74 -> #REF! | L74: =E74*CAOP!J74 -> #REF! | M74: =E74*CAOP!K74 -> #REF! | N74: =E74*CAOP!L74 -> #REF! | O74: =E74*CAOP!M74 -> #REF! | Q74: =SUM(F74:O74) -> #REF! | R74: =E74-Q74 -> #REF!
B75: 04.02.11 | C75: TRANSPORTE DE MATERIAL DE ELIMINACION D>1KM | D75: m3-km | E75: 478.15 | F75: =E75*CAOP!D75 -> #REF! | G75: =E75*CAOP!E75 -> #REF! | H75: =E75*CAOP!F75 -> #REF! | I75: =E75*CAOP!G75 -> #REF! | J75: =E75*CAOP!H75 -> #REF! | K75: =E75*CAOP!I75 -> #REF! | L75: =E75*CAOP!J75 -> #REF! | M75: =E75*CAOP!K75 -> #REF! | N75: =E75*CAOP!L75 -> #REF! | O75: =E75*CAOP!M75 -> #REF! | Q75: =SUM(F75:O75) -> #REF! | R75: =E75-Q75 -> #REF!
B76: 04.03 | C76: ACCESOS 3 Y 4 | Q76: =SUM(F76:O76) -> 0 | R76: =E76-Q76 -> 0
B77: 04.03.01 | C77: TRAZO Y REPLANTEO PARA OBRAS VIALES | D77: km | E77: 0.27 | F77: =E77*CAOP!D77 -> #REF! | G77: =E77*CAOP!E77 -> #REF! | H77: =E77*CAOP!F77 -> #REF! | I77: =E77*CAOP!G77 -> #REF! | J77: =E77*CAOP!H77 -> #REF! | K77: =E77*CAOP!I77 -> #REF! | L77: =E77*CAOP!J77 -> #REF! | M77: =E77*CAOP!K77 -> #REF! | N77: =E77*CAOP!L77 -> #REF! | O77: =E77*CAOP!M77 -> #REF! | Q77: =SUM(F77:O77) -> #REF! | R77: =E77-Q77 -> #REF!
B78: 04.03.02 | C78: EXCAVACION C/MAQ. EN TERRENO NORMAL H<=2M | D78: m3 | E78: 543.05 | F78: =E78*CAOP!D78 -> #REF! | G78: =E78*CAOP!E78 -> #REF! | H78: =E78*CAOP!F78 -> #REF! | I78: =E78*CAOP!G78 -> #REF! | J78: =E78*CAOP!H78 -> #REF! | K78: =E78*CAOP!I78 -> #REF! | L78: =E78*CAOP!J78 -> #REF! | M78: =E78*CAOP!K78 -> #REF! | N78: =E78*CAOP!L78 -> #REF! | O78: =E78*CAOP!M78 -> #REF! | Q78: =SUM(F78:O78) -> #REF! | R78: =E78-Q78 -> #REF!
B79: 04.03.03 | C79: ACARREO DE MATERIAL PROVENIENTE DE EXCAVACIONES, D<= 1KM | D79: m3-km | E79: 543.05 | F79: =E79*CAOP!D79 -> #REF! | G79: =E79*CAOP!E79 -> #REF! | H79: =E79*CAOP!F79 -> #REF! | I79: =E79*CAOP!G79 -> #REF! | J79: =E79*CAOP!H79 -> #REF! | K79: =E79*CAOP!I79 -> #REF! | L79: =E79*CAOP!J79 -> #REF! | M79: =E79*CAOP!K79 -> #REF! | N79: =E79*CAOP!L79 -> #REF! | O79: =E79*CAOP!M79 -> #REF! | Q79: =SUM(F79:O79) -> #REF! | R79: =E79-Q79 -> #REF!
B80: 04.03.04 | C80: RELLENO COMPACTADO CON MATERIAL PROPIO | D80: m3 | E80: 1630.5 | F80: =E80*CAOP!D80 -> #REF! | G80: =E80*CAOP!E80 -> #REF! | H80: =E80*CAOP!F80 -> #REF! | I80: =E80*CAOP!G80 -> #REF! | J80: =E80*CAOP!H80 -> #REF! | K80: =E80*CAOP!I80 -> #REF! | L80: =E80*CAOP!J80 -> #REF! | M80: =E80*CAOP!K80 -> #REF! | N80: =E80*CAOP!L80 -> #REF! | O80: =E80*CAOP!M80 -> #REF! | Q80: =SUM(F80:O80) -> #REF! | R80: =E80-Q80 -> #REF!
B81: 04.03.05 | C81: PERFILADO Y COMPACTADO EN ZONAS DE CORTE | D81: m2 | E81: 1620 | F81: =E81*CAOP!D81 -> #REF! | G81: =E81*CAOP!E81 -> #REF! | H81: =E81*CAOP!F81 -> #REF! | I81: =E81*CAOP!G81 -> #REF! | J81: =E81*CAOP!H81 -> #REF! | K81: =E81*CAOP!I81 -> #REF! | L81: =E81*CAOP!J81 -> #REF! | M81: =E81*CAOP!K81 -> #REF! | N81: =E81*CAOP!L81 -> #REF! | O81: =E81*CAOP!M81 -> #REF! | Q81: =SUM(F81:O81) -> #REF! | R81: =E81-Q81 -> #REF!
B82: 04.03.06 | C82: CONFORMACION DE TERRENO CON MATERIAL DE AFIRMADO (E=0.20M) | D82: m3 | E82: 403.08 | F82: =E82*CAOP!D82 -> #REF! | G82: =E82*CAOP!E82 -> #REF! | H82: =E82*CAOP!F82 -> #REF! | I82: =E82*CAOP!G82 -> #REF! | J82: =E82*CAOP!H82 -> #REF! | K82: =E82*CAOP!I82 -> #REF! | L82: =E82*CAOP!J82 -> #REF! | M82: =E82*CAOP!K82 -> #REF! | N82: =E82*CAOP!L82 -> #REF! | O82: =E82*CAOP!M82 -> #REF! | Q82: =SUM(F82:O82) -> #REF! | R82: =E82-Q82 -> #REF!
B83: 04.03.07 | C83: SUMINISTRO EN PUNTO DE ACOPIO DE MATERIAL DE PRESTAMO (AFIRMADO) | D83: m3 | E83: 403.08 | F83: =E83*CAOP!D83 -> #REF! | G83: =E83*CAOP!E83 -> #REF! | H83: =E83*CAOP!F83 -> #REF! | I83: =E83*CAOP!G83 -> #REF! | J83: =E83*CAOP!H83 -> #REF! | K83: =E83*CAOP!I83 -> #REF! | L83: =E83*CAOP!J83 -> #REF! | M83: =E83*CAOP!K83 -> #REF! | N83: =E83*CAOP!L83 -> #REF! | O83: =E83*CAOP!M83 -> #REF! | Q83: =SUM(F83:O83) -> #REF! | R83: =E83-Q83 -> #REF!
B84: 04.03.08 | C84: TRANSPORTE DE MATERIAL GRANULAR, D<=1KM | D84: m3-km | E84: 1789.54 | F84: =E84*CAOP!D84 -> #REF! | G84: =E84*CAOP!E84 -> #REF! | H84: =E84*CAOP!F84 -> #REF! | I84: =E84*CAOP!G84 -> #REF! | J84: =E84*CAOP!H84 -> #REF! | K84: =E84*CAOP!I84 -> #REF! | L84: =E84*CAOP!J84 -> #REF! | M84: =E84*CAOP!K84 -> #REF! | N84: =E84*CAOP!L84 -> #REF! | O84: =E84*CAOP!M84 -> #REF! | Q84: =SUM(F84:O84) -> #REF! | R84: =E84-Q84 -> #REF!
B85: 04.03.09 | C85: TRANSPORTE DE MATERIAL GRANULAR, D>1KM | D85: m3-km | E85: 6792.44 | F85: =E85*CAOP!D85 -> #REF! | G85: =E85*CAOP!E85 -> #REF! | H85: =E85*CAOP!F85 -> #REF! | I85: =E85*CAOP!G85 -> #REF! | J85: =E85*CAOP!H85 -> #REF! | K85: =E85*CAOP!I85 -> #REF! | L85: =E85*CAOP!J85 -> #REF! | M85: =E85*CAOP!K85 -> #REF! | N85: =E85*CAOP!L85 -> #REF! | O85: =E85*CAOP!M85 -> #REF! | Q85: =SUM(F85:O85) -> #REF! | R85: =E85-Q85 -> #REF!
B86: 04.03.10 | C86: TRANSPORTE DE MATERIAL DE ELIMINACION D<=1KM | D86: m3-km | E86: 477.88 | F86: =E86*CAOP!D86 -> #REF! | G86: =E86*CAOP!E86 -> #REF! | H86: =E86*CAOP!F86 -> #REF! | I86: =E86*CAOP!G86 -> #REF! | J86: =E86*CAOP!H86 -> #REF! | K86: =E86*CAOP!I86 -> #REF! | L86: =E86*CAOP!J86 -> #REF! | M86: =E86*CAOP!K86 -> #REF! | N86: =E86*CAOP!L86 -> #REF! | O86: =E86*CAOP!M86 -> #REF! | Q86: =SUM(F86:O86) -> #REF! | R86: =E86-Q86 -> #REF!
B87: 04.03.11 | C87: TRANSPORTE DE MATERIAL DE ELIMINACION D>1KM | D87: m3-km | E87: 368.11 | F87: =E87*CAOP!D87 -> #REF! | G87: =E87*CAOP!E87 -> #REF! | H87: =E87*CAOP!F87 -> #REF! | I87: =E87*CAOP!G87 -> #REF! | J87: =E87*CAOP!H87 -> #REF! | K87: =E87*CAOP!I87 -> #REF! | L87: =E87*CAOP!J87 -> #REF! | M87: =E87*CAOP!K87 -> #REF! | N87: =E87*CAOP!L87 -> #REF! | O87: =E87*CAOP!M87 -> #REF! | Q87: =SUM(F87:O87) -> #REF! | R87: =E87-Q87 -> #REF!
B88: 05 | C88: COMPONENTE 04 - CANAL Y ESTABILIZACION DE TALUD - JESUS MARIA | Q88: =SUM(F88:O88) -> 0 | R88: =E88-Q88 -> 0
B89: 05.01 | C89: CANAL EXISTENTE | Q89: =SUM(F89:O89) -> 0 | R89: =E89-Q89 -> 0
B90: 05.01.01 | C90: CINTA PLASTICA SENALIZADORA PARA LIMITE DE SEGURIDAD DE OBRA | D90: m | E90: 1013.06 | F90: =E90*CAOP!D90 -> #REF! | G90: =E90*CAOP!E90 -> #REF! | H90: =E90*CAOP!F90 -> #REF! | I90: =E90*CAOP!G90 -> #REF! | J90: =E90*CAOP!H90 -> #REF! | K90: =E90*CAOP!I90 -> #REF! | L90: =E90*CAOP!J90 -> #REF! | M90: =E90*CAOP!K90 -> #REF! | N90: =E90*CAOP!L90 -> #REF! | O90: =E90*CAOP!M90 -> #REF! | Q90: =SUM(F90:O90) -> #REF! | R90: =E90-Q90 -> #REF!
B91: 05.01.02 | C91: CERCO DE MALLA HDPE DE 1M DE ALTURA PARA LIMITE DE SEGURIDAD DE OBRA | D91: m | E91: 1013.06 | F91: =E91*CAOP!D91 -> #REF! | G91: =E91*CAOP!E91 -> #REF! | H91: =E91*CAOP!F91 -> #REF! | I91: =E91*CAOP!G91 -> #REF! | J91: =E91*CAOP!H91 -> #REF! | K91: =E91*CAOP!I91 -> #REF! | L91: =E91*CAOP!J91 -> #REF! | M91: =E91*CAOP!K91 -> #REF! | N91: =E91*CAOP!L91 -> #REF! | O91: =E91*CAOP!M91 -> #REF! | Q91: =SUM(F91:O91) -> #REF! | R91: =E91-Q91 -> #REF!
B92: 05.01.03 | C92: EXCAVACION C/MAQ. EN TERRENO NORMAL H<=2M | D92: m3 | E92: 652.29 | F92: =E92*CAOP!D92 -> #REF! | G92: =E92*CAOP!E92 -> #REF! | H92: =E92*CAOP!F92 -> #REF! | I92: =E92*CAOP!G92 -> #REF! | J92: =E92*CAOP!H92 -> #REF! | K92: =E92*CAOP!I92 -> #REF! | L92: =E92*CAOP!J92 -> #REF! | M92: =E92*CAOP!K92 -> #REF! | N92: =E92*CAOP!L92 -> #REF! | O92: =E92*CAOP!M92 -> #REF! | Q92: =SUM(F92:O92) -> #REF! | R92: =E92-Q92 -> #REF!
B93: 05.01.04 | C93: DEMOLICIÓN DE ESTRUCTURAS DE CONCRETO | D93: m3 | E93: 1019.98 | F93: =E93*CAOP!D93 -> #REF! | G93: =E93*CAOP!E93 -> #REF! | H93: =E93*CAOP!F93 -> #REF! | I93: =E93*CAOP!G93 -> #REF! | J93: =E93*CAOP!H93 -> #REF! | K93: =E93*CAOP!I93 -> #REF! | L93: =E93*CAOP!J93 -> #REF! | M93: =E93*CAOP!K93 -> #REF! | N93: =E93*CAOP!L93 -> #REF! | O93: =E93*CAOP!M93 -> #REF! | Q93: =SUM(F93:O93) -> #REF! | R93: =E93-Q93 -> #REF!
B94: 05.01.05 | C94: ELIMINACIÓN DE MATERIAL PROVENIENTE DE DEMOLICIONES | D94: m3 | E94: 1019.98 | F94: =E94*CAOP!D94 -> #REF! | G94: =E94*CAOP!E94 -> #REF! | H94: =E94*CAOP!F94 -> #REF! | I94: =E94*CAOP!G94 -> #REF! | J94: =E94*CAOP!H94 -> #REF! | K94: =E94*CAOP!I94 -> #REF! | L94: =E94*CAOP!J94 -> #REF! | M94: =E94*CAOP!K94 -> #REF! | N94: =E94*CAOP!L94 -> #REF! | O94: =E94*CAOP!M94 -> #REF! | Q94: =SUM(F94:O94) -> #REF! | R94: =E94-Q94 -> #REF!
B95: 05.01.06 | C95: TRANSPORTE DE MATERIAL DE ELIMINACION D<=1KM | D95: m3-km | E95: 574.09 | F95: =E95*CAOP!D95 -> #REF! | G95: =E95*CAOP!E95 -> #REF! | H95: =E95*CAOP!F95 -> #REF! | I95: =E95*CAOP!G95 -> #REF! | J95: =E95*CAOP!H95 -> #REF! | K95: =E95*CAOP!I95 -> #REF! | L95: =E95*CAOP!J95 -> #REF! | M95: =E95*CAOP!K95 -> #REF! | N95: =E95*CAOP!L95 -> #REF! | O95: =E95*CAOP!M95 -> #REF! | Q95: =SUM(F95:O95) -> #REF! | R95: =E95-Q95 -> #REF!
B96: 05.01.07 | C96: TRANSPORTE DE MATERIAL DE ELIMINACION D>1KM | D96: m3-km | E96: 1903.53 | F96: =E96*CAOP!D96 -> #REF! | G96: =E96*CAOP!E96 -> #REF! | H96: =E96*CAOP!F96 -> #REF! | I96: =E96*CAOP!G96 -> #REF! | J96: =E96*CAOP!H96 -> #REF! | K96: =E96*CAOP!I96 -> #REF! | L96: =E96*CAOP!J96 -> #REF! | M96: =E96*CAOP!K96 -> #REF! | N96: =E96*CAOP!L96 -> #REF! | O96: =E96*CAOP!M96 -> #REF! | Q96: =SUM(F96:O96) -> #REF! | R96: =E96-Q96 -> #REF!
B97: 05.02 | C97: ESTRUCTURA DE DESCARGA Y DISIPADOR DE ENERGIA (QUEBRADA SANTA RITA) | Q97: =SUM(F97:O97) -> 0 | R97: =E97-Q97 -> 0
B98: 05.02.01 | C98: OBRAS PRELIMINARES | Q98: =SUM(F98:O98) -> 0 | R98: =E98-Q98 -> 0
B99: 05.02.01.01 | C99: LIMPIEZA INICIAL DEL TERRENO CON EQUIPO | D99: m2 | E99: 2484.84 | F99: =E99*CAOP!D99 -> #REF! | G99: =E99*CAOP!E99 -> #REF! | H99: =E99*CAOP!F99 -> #REF! | I99: =E99*CAOP!G99 -> #REF! | J99: =E99*CAOP!H99 -> #REF! | K99: =E99*CAOP!I99 -> #REF! | L99: =E99*CAOP!J99 -> #REF! | M99: =E99*CAOP!K99 -> #REF! | N99: =E99*CAOP!L99 -> #REF! | O99: =E99*CAOP!M99 -> #REF! | Q99: =SUM(F99:O99) -> #REF! | R99: =E99-Q99 -> #REF!
B100: 05.02.01.02 | C100: ELIMINACIÓN DE RESIDUOS SÓLIDOS | D100: m3 | E100: 372.73 | F100: =E100*CAOP!D100 -> #REF! | G100: =E100*CAOP!E100 -> #REF! | H100: =E100*CAOP!F100 -> #REF! | I100: =E100*CAOP!G100 -> #REF! | J100: =E100*CAOP!H100 -> #REF! | K100: =E100*CAOP!I100 -> #REF! | L100: =E100*CAOP!J100 -> #REF! | M100: =E100*CAOP!K100 -> #REF! | N100: =E100*CAOP!L100 -> #REF! | O100: =E100*CAOP!M100 -> #REF! | Q100: =SUM(F100:O100) -> #REF! | R100: =E100-Q100 -> #REF!
B101: 05.02.01.03 | C101: TRAZO Y REPLANTEO PARA ESTRUCTURAS | D101: m2 | E101: 940.36 | F101: =E101*CAOP!D101 -> #REF! | G101: =E101*CAOP!E101 -> #REF! | H101: =E101*CAOP!F101 -> #REF! | I101: =E101*CAOP!G101 -> #REF! | J101: =E101*CAOP!H101 -> #REF! | K101: =E101*CAOP!I101 -> #REF! | L101: =E101*CAOP!J101 -> #REF! | M101: =E101*CAOP!K101 -> #REF! | N101: =E101*CAOP!L101 -> #REF! | O101: =E101*CAOP!M101 -> #REF! | Q101: =SUM(F101:O101) -> #REF! | R101: =E101-Q101 -> #REF!
B102: 05.02.01.04 | C102: CINTA PLASTICA SENALIZADORA PARA LIMITE DE SEGURIDAD DE OBRA | D102: m | E102: 382.13 | F102: =E102*CAOP!D102 -> #REF! | G102: =E102*CAOP!E102 -> #REF! | H102: =E102*CAOP!F102 -> #REF! | I102: =E102*CAOP!G102 -> #REF! | J102: =E102*CAOP!H102 -> #REF! | K102: =E102*CAOP!I102 -> #REF! | L102: =E102*CAOP!J102 -> #REF! | M102: =E102*CAOP!K102 -> #REF! | N102: =E102*CAOP!L102 -> #REF! | O102: =E102*CAOP!M102 -> #REF! | Q102: =SUM(F102:O102) -> #REF! | R102: =E102-Q102 -> #REF!
B103: 05.02.01.05 | C103: CERCO DE MALLA HDPE DE 1M DE ALTURA PARA LIMITE DE SEGURIDAD DE OBRA | D103: m | E103: 382.13 | F103: =E103*CAOP!D103 -> #REF! | G103: =E103*CAOP!E103 -> #REF! | H103: =E103*CAOP!F103 -> #REF! | I103: =E103*CAOP!G103 -> #REF! | J103: =E103*CAOP!H103 -> #REF! | K103: =E103*CAOP!I103 -> #REF! | L103: =E103*CAOP!J103 -> #REF! | M103: =E103*CAOP!K103 -> #REF! | N103: =E103*CAOP!L103 -> #REF! | O103: =E103*CAOP!M103 -> #REF! | Q103: =SUM(F103:O103) -> #REF! | R103: =E103-Q103 -> #REF!
B104: 05.02.02 | C104: MOVIMIENTO DE TIERRAS | Q104: =SUM(F104:O104) -> 0 | R104: =E104-Q104 -> 0
B105: 05.02.02.01 | C105: EXCAVACION C/MAQ. EN TERRENO NORMAL H<=2M | D105: m3 | E105: 5786.33 | F105: =E105*CAOP!D105 -> #REF! | G105: =E105*CAOP!E105 -> #REF! | H105: =E105*CAOP!F105 -> #REF! | I105: =E105*CAOP!G105 -> #REF! | J105: =E105*CAOP!H105 -> #REF! | K105: =E105*CAOP!I105 -> #REF! | L105: =E105*CAOP!J105 -> #REF! | M105: =E105*CAOP!K105 -> #REF! | N105: =E105*CAOP!L105 -> #REF! | O105: =E105*CAOP!M105 -> #REF! | Q105: =SUM(F105:O105) -> #REF! | R105: =E105-Q105 -> #REF!
B106: 05.02.02.02 | C106: EXCAVACION MANUAL PARA ANCLAJE DE GEOTEXTIL | D106: m3 | E106: 12.96 | F106: =E106*CAOP!D106 -> #REF! | G106: =E106*CAOP!E106 -> #REF! | H106: =E106*CAOP!F106 -> #REF! | I106: =E106*CAOP!G106 -> #REF! | J106: =E106*CAOP!H106 -> #REF! | K106: =E106*CAOP!I106 -> #REF! | L106: =E106*CAOP!J106 -> #REF! | M106: =E106*CAOP!K106 -> #REF! | N106: =E106*CAOP!L106 -> #REF! | O106: =E106*CAOP!M106 -> #REF! | Q106: =SUM(F106:O106) -> #REF! | R106: =E106-Q106 -> #REF!
B107: 05.02.02.03 | C107: CONFORMACIÓN, NIVELACIÓN Y COMPACTACIÓN DE FONDO DE EXCAVACION PARA ESTRUCTURAS | D107: m2 | E107: 963.03 | F107: =E107*CAOP!D107 -> #REF! | G107: =E107*CAOP!E107 -> #REF! | H107: =E107*CAOP!F107 -> #REF! | I107: =E107*CAOP!G107 -> #REF! | J107: =E107*CAOP!H107 -> #REF! | K107: =E107*CAOP!I107 -> #REF! | L107: =E107*CAOP!J107 -> #REF! | M107: =E107*CAOP!K107 -> #REF! | N107: =E107*CAOP!L107 -> #REF! | O107: =E107*CAOP!M107 -> #REF! | Q107: =SUM(F107:O107) -> #REF! | R107: =E107-Q107 -> #REF!
B108: 05.02.02.04 | C108: SUMINISTRO EN PUNTO DE ACOPIO DE MATERIAL DE PRÉSTAMO (RELLENO ESTRUCTURAL) | D108: m3 | E108: 1470.5 | F108: =E108*CAOP!D108 -> #REF! | G108: =E108*CAOP!E108 -> #REF! | H108: =E108*CAOP!F108 -> #REF! | I108: =E108*CAOP!G108 -> #REF! | J108: =E108*CAOP!H108 -> #REF! | K108: =E108*CAOP!I108 -> #REF! | L108: =E108*CAOP!J108 -> #REF! | M108: =E108*CAOP!K108 -> #REF! | N108: =E108*CAOP!L108 -> #REF! | O108: =E108*CAOP!M108 -> #REF! | Q108: =SUM(F108:O108) -> #REF! | R108: =E108-Q108 -> #REF!
B109: 05.02.02.05 | C109: SUMINISTRO EN PUNTO DE ACOPIO DE PIEDRA CANTO RODADO DE 6" A 10" | D109: m3 | E109: 656.4 | F109: =E109*CAOP!D109 -> #REF! | G109: =E109*CAOP!E109 -> #REF! | H109: =E109*CAOP!F109 -> #REF! | I109: =E109*CAOP!G109 -> #REF! | J109: =E109*CAOP!H109 -> #REF! | K109: =E109*CAOP!I109 -> #REF! | L109: =E109*CAOP!J109 -> #REF! | M109: =E109*CAOP!K109 -> #REF! | N109: =E109*CAOP!L109 -> #REF! | O109: =E109*CAOP!M109 -> #REF! | Q109: =SUM(F109:O109) -> #REF! | R109: =E109-Q109 -> #REF!
B110: 05.02.02.06 | C110: RELLENO COMPACTADO PARA ESTRUCTURAS | D110: m3 | E110: 1470.5 | F110: =E110*CAOP!D110 -> #REF! | G110: =E110*CAOP!E110 -> #REF! | H110: =E110*CAOP!F110 -> #REF! | I110: =E110*CAOP!G110 -> #REF! | J110: =E110*CAOP!H110 -> #REF! | K110: =E110*CAOP!I110 -> #REF! | L110: =E110*CAOP!J110 -> #REF! | M110: =E110*CAOP!K110 -> #REF! | N110: =E110*CAOP!L110 -> #REF! | O110: =E110*CAOP!M110 -> #REF! | Q110: =SUM(F110:O110) -> #REF! | R110: =E110-Q110 -> #REF!
B111: 05.02.02.07 | C111: TRANSPORTE DE PIEDRA PARA GAVIÓN, D<= 1 KM | D111: m3-km | E111: 577.63 | F111: =E111*CAOP!D111 -> #REF! | G111: =E111*CAOP!E111 -> #REF! | H111: =E111*CAOP!F111 -> #REF! | I111: =E111*CAOP!G111 -> #REF! | J111: =E111*CAOP!H111 -> #REF! | K111: =E111*CAOP!I111 -> #REF! | L111: =E111*CAOP!J111 -> #REF! | M111: =E111*CAOP!K111 -> #REF! | N111: =E111*CAOP!L111 -> #REF! | O111: =E111*CAOP!M111 -> #REF! | Q111: =SUM(F111:O111) -> #REF! | R111: =E111-Q111 -> #REF!
B112: 05.02.02.08 | C112: TRANSPORTE DE PIEDRA PARA GAVIÓN, D>1 KM | D112: m3-km | E112: 2298.77 | F112: =E112*CAOP!D112 -> #REF! | G112: =E112*CAOP!E112 -> #REF! | H112: =E112*CAOP!F112 -> #REF! | I112: =E112*CAOP!G112 -> #REF! | J112: =E112*CAOP!H112 -> #REF! | K112: =E112*CAOP!I112 -> #REF! | L112: =E112*CAOP!J112 -> #REF! | M112: =E112*CAOP!K112 -> #REF! | N112: =E112*CAOP!L112 -> #REF! | O112: =E112*CAOP!M112 -> #REF! | Q112: =SUM(F112:O112) -> #REF! | R112: =E112-Q112 -> #REF!
B113: 05.02.02.09 | C113: TRANSPORTE DE MATERIAL GRANULAR, D<=1KM | D113: m3-km | E113: 1294.04 | F113: =E113*CAOP!D113 -> #REF! | G113: =E113*CAOP!E113 -> #REF! | H113: =E113*CAOP!F113 -> #REF! | I113: =E113*CAOP!G113 -> #REF! | J113: =E113*CAOP!H113 -> #REF! | K113: =E113*CAOP!I113 -> #REF! | L113: =E113*CAOP!J113 -> #REF! | M113: =E113*CAOP!K113 -> #REF! | N113: =E113*CAOP!L113 -> #REF! | O113: =E113*CAOP!M113 -> #REF! | Q113: =SUM(F113:O113) -> #REF! | R113: =E113-Q113 -> #REF!
B114: 05.02.02.10 | C114: TRANSPORTE DE MATERIAL GRANULAR, D>1KM | D114: m3-km | E114: 5848.88 | F114: =E114*CAOP!D114 -> #REF! | G114: =E114*CAOP!E114 -> #REF! | H114: =E114*CAOP!F114 -> #REF! | I114: =E114*CAOP!G114 -> #REF! | J114: =E114*CAOP!H114 -> #REF! | K114: =E114*CAOP!I114 -> #REF! | L114: =E114*CAOP!J114 -> #REF! | M114: =E114*CAOP!K114 -> #REF! | N114: =E114*CAOP!L114 -> #REF! | O114: =E114*CAOP!M114 -> #REF! | Q114: =SUM(F114:O114) -> #REF! | R114: =E114-Q114 -> #REF!
B115: 05.02.02.11 | C115: TRANSPORTE DE MATERIAL DE ELIMINACION D<=1KM | D115: m3-km | E115: 2374.68 | F115: =E115*CAOP!D115 -> #REF! | G115: =E115*CAOP!E115 -> #REF! | H115: =E115*CAOP!F115 -> #REF! | I115: =E115*CAOP!G115 -> #REF! | J115: =E115*CAOP!H115 -> #REF! | K115: =E115*CAOP!I115 -> #REF! | L115: =E115*CAOP!J115 -> #REF! | M115: =E115*CAOP!K115 -> #REF! | N115: =E115*CAOP!L115 -> #REF! | O115: =E115*CAOP!M115 -> #REF! | Q115: =SUM(F115:O115) -> #REF! | R115: =E115-Q115 -> #REF!
...

Sheet CURVA S
D1: CURVA S DEL PAQUETE 08
D3: “CONSTRUCCIÓN DEL SISTEMA DE DRENAJE URBANO EN EL SECTOR JESÚS MARÍA – CANAL Y OBRAS DE ESTABILIZACIÓN EN LAS LADERAS DEL SECTOR JESÚS MARÍA (PAQUETE 08)”
B5: MES | C5: MONTO | E5: PORCENTAJE
C6: PARCIAL (S/) | D6: ACUMULADO (S/) | E6: PARCIAL (%) | F6: ACUMULADO (%)
B7: 1 | C7: {=TRANSPOSE(PPTO!#REF!)} -> #REF! | D7: =+C7 -> #REF! | E7: =+C7/D$16 -> #REF! | F7: =E7 -> #REF!
B8: 2 | D8: =+C8+D7 -> #REF! | E8: =+C8/D$16 -> #REF! | F8: =+E8+F7 -> #REF!
B9: 3 | D9: =+C9+D8 -> #REF! | E9: =+C9/D$16 -> #REF! | F9: =+E9+F8 -> #REF!
B10: 4 | D10: =+C10+D9 -> #REF! | E10: =+C10/D$16 -> #REF! | F10: =+E10+F9 -> #REF!
B11: 5 | D11: =+C11+D10 -> #REF! | E11: =+C11/D$16 -> #REF! | F11: =+E11+F10 -> #REF!
B12: 6 | D12: =+C12+D11 -> #REF! | E12: =+C12/D$16 -> #REF! | F12: =+E12+F11 -> #REF!
B13: 7 | D13: =+C13+D12 -> #REF! | E13: =+C13/D$16 -> #REF! | F13: =+E13+F12 -> #REF!
B14: 8 | D14: =+C14+D13 -> #REF! | E14: =+C14/D$16 -> #REF! | F14: =+E14+F13 -> #REF!
B15: 9 | D15: =+C15+D14 -> #REF! | E15: =+C15/D$16 -> #REF! | F15: =+E15+F14 -> #REF!
B16: 10 | D16: =+C16+D15 -> #REF! | E16: =+C16/D$16 -> #REF! | F16: =+E16+F15 -> #REF!
